{"copyright": "NHL and the NHL Shield are registered trademarks of the National Hockey League. NHL and NHL team marks are the property of the NHL and its teams. \u00a9 NHL 2019. All Rights Reserved.", "teams": {"away": {"team": {"id": 17, "name": "Detroit Red Wings", "link": "/api/v1/teams/17"}, "teamStats": {"teamSkaterStats": {"goals": 3, "pim": 4, "shots": 31, "powerPlayPercentage": "0.0", "powerPlayGoals": 0.0, "powerPlayOpportunities": 2.0, "faceOffWinPercentage": "52.7", "blocked": 15, "takeaways": 10, "giveaways": 2, "hits": 27}}, "players": {"ID8470318": {"person": {"id": 8470318, "fullName": "Jonathan Ericsson", "link": "/api/v1/people/8470318", "firstName": "Jonathan", "lastName": "Ericsson", "primaryNumber": "52", "birthDate": "1984-03-02", "currentAge": 35, "birthCity": "Karlskrona", "birthCountry": "SWE", "nationality": "SWE", "height": "6' 4\"", "weight": 220, "active": true, "alternateCaptain": false, "captain": false, "rookie": false, "shootsCatches": "L", "rosterStatus": "I", "currentTeam": {"id": 17, "name": "Detroit Red Wings", "link": "/api/v1/teams/17"}, "primaryPosition": {"code": "D", "name": "Defenseman", "type": "Defenseman", "abbreviation": "D"}}, "jerseyNumber": "52", "position": {"code": "D", "name": "Defenseman", "type": "Defenseman", "abbreviation": "D"}, "stats": {"skaterStats": {"timeOnIce": "16:49", "assists": 0, "goals": 0, "shots": 1, "hits": 4, "powerPlayGoals": 0, "powerPlayAssists": 0, "penaltyMinutes": 2, "faceOffWins": 0, "faceoffTaken": 0, "takeaways": 0, "giveaways": 0, "shortHandedGoals": 0, "shortHandedAssists": 0, "blocked": 0, "plusMinus": 0, "evenTimeOnIce": "15:37", "powerPlayTimeOnIce": "0:00", "shortHandedTimeOnIce": "1:12"}}}, "ID8470778": {"person": {"id": 8470778, "fullName": "Drew Miller", "link": "/api/v1/people/8470778", "firstName": "Drew", "lastName": "Miller", "primaryNumber": "20", "birthDate": "1984-02-17", "birthCity": "Dover", "birthStateProvince": "NJ", "birthCountry": "USA", "nationality": "USA", "height": "6' 2\"", "weight": 183, "active": false, "rookie": false, "shootsCatches": "L", "rosterStatus": "N", "primaryPosition": {"code": "L", "name": "Left Wing", "type": "Forward", "abbreviation": "LW"}}, "jerseyNumber": "20", "position": {"code": "L", "name": "Left Wing", "type": "Forward", "abbreviation": "LW"}, "stats": {"skaterStats": {"timeOnIce": "6:56", "assists": 0, "goals": 0, "shots": 3, "hits": 5, "powerPlayGoals": 0, "powerPlayAssists": 0, "penaltyMinutes": 0, "faceOffWins": 0, "faceoffTaken": 0, "takeaways": 1, "giveaways": 0, "shortHandedGoals": 0, "shortHandedAssists": 0, "blocked": 1, "plusMinus": -2, "evenTimeOnIce": "6:56", "powerPlayTimeOnIce": "0:00", "shortHandedTimeOnIce": "0:00"}}}, "ID8474679": {"person": {"id": 8474679, "fullName": "Gustav Nyquist", "link": "/api/v1/people/8474679", "firstName": "Gustav", "lastName": "Nyquist", "primaryNumber": "14", "birthDate": "1989-09-01", "currentAge": 29, "birthCity": "Halmstad", "birthCountry": "SWE", "nationality": "SWE", "height": "5' 11\"", "weight": 184, "active": true, "alternateCaptain": false, "captain": false, "rookie": false, "shootsCatches": "L", "rosterStatus": "Y", "currentTeam": {"id": 17, "name": "Detroit Red Wings", "link": "/api/v1/teams/17"}, "primaryPosition": {"code": "R", "name": "Right Wing", "type": "Forward", "abbreviation": "RW"}}, "jerseyNumber": "14", "position": {"code": "R", "name": "Right Wing", "type": "Forward", "abbreviation": "RW"}, "stats": {"skaterStats": {"timeOnIce": "17:04", "assists": 0, "goals": 0, "shots": 2, "hits": 1, "powerPlayGoals": 0, "powerPlayAssists": 0, "penaltyMinutes": 0, "faceOffPct": 100.0, "faceOffWins": 1, "faceoffTaken": 1, "takeaways": 0, "giveaways": 1, "shortHandedGoals": 0, "shortHandedAssists": 0, "blocked": 1, "plusMinus": -2, "evenTimeOnIce": "15:11", "powerPlayTimeOnIce": "1:53", "shortHandedTimeOnIce": "0:00"}}}, "ID8477946": {"person": {"id": 8477946, "fullName": "Dylan Larkin", "link": "/api/v1/people/8477946", "firstName": "Dylan", "lastName": "Larkin", "primaryNumber": "71", "birthDate": "1996-07-30", "currentAge": 22, "birthCity": "Waterford", "birthStateProvince": "MI", "birthCountry": "USA", "nationality": "USA", "height": "6' 1\"", "weight": 190, "active": true, "alternateCaptain": false, "captain": false, "rookie": false, "shootsCatches": "L", "rosterStatus": "Y", "currentTeam": {"id": 17, "name": "Detroit Red Wings", "link": "/api/v1/teams/17"}, "primaryPosition": {"code": "C", "name": "Center", "type": "Forward", "abbreviation": "C"}}, "jerseyNumber": "71", "position": {"code": "C", "name": "Center", "type": "Forward", "abbreviation": "C"}, "stats": {"skaterStats": {"timeOnIce": "16:54", "assists": 0, "goals": 1, "shots": 1, "hits": 0, "powerPlayGoals": 0, "powerPlayAssists": 0, "penaltyMinutes": 0, "faceOffPct": 42.86, "faceOffWins": 3, "faceoffTaken": 7, "takeaways": 1, "giveaways": 0, "shortHandedGoals": 0, "shortHandedAssists": 0, "blocked": 1, "plusMinus": 0, "evenTimeOnIce": "15:12", "powerPlayTimeOnIce": "1:42", "shortHandedTimeOnIce": "0:00"}}}, "ID8470144": {"person": {"id": 8470144, "fullName": "Frans Nielsen", "link": "/api/v1/people/8470144", "firstName": "Frans", "lastName": "Nielsen", "primaryNumber": "51", "birthDate": "1984-04-24", "currentAge": 34, "birthCity": "Herning", "birthCountry": "DNK", "nationality": "DNK", "height": "6' 1\"", "weight": 188, "active": true, "alternateCaptain": false, "captain": false, "rookie": false, "shootsCatches": "L", "rosterStatus": "Y", "currentTeam": {"id": 17, "name": "Detroit Red Wings", "link": "/api/v1/teams/17"}, "primaryPosition": {"code": "C", "name": "Center", "type": "Forward", "abbreviation": "C"}}, "jerseyNumber": "51", "position": {"code": "C", "name": "Center", "type": "Forward", "abbreviation": "C"}, "stats": {"skaterStats": {"timeOnIce": "14:23", "assists": 0, "goals": 1, "shots": 1, "hits": 0, "powerPlayGoals": 0, "powerPlayAssists": 0, "penaltyMinutes": 0, "faceOffPct": 60.0, "faceOffWins": 9, "faceoffTaken": 15, "takeaways": 1, "giveaways": 0, "shortHandedGoals": 0, "shortHandedAssists": 0, "blocked": 0, "plusMinus": 1, "evenTimeOnIce": "11:08", "powerPlayTimeOnIce": "1:37", "shortHandedTimeOnIce": "1:38"}}}, "ID8474873": {"person": {"id": 8474873, "fullName": "Brian Lashoff", "link": "/api/v1/people/8474873", "firstName": "Brian", "lastName": "Lashoff", "primaryNumber": "23", "birthDate": "1990-07-16", "currentAge": 28, "birthCity": "Albany", "birthStateProvince": "NY", "birthCountry": "USA", "nationality": "USA", "height": "6' 3\"", "weight": 221, "active": true, "alternateCaptain": false, "captain": false, "rookie": false, "shootsCatches": "L", "rosterStatus": "N", "currentTeam": {"id": 17, "name": "Detroit Red Wings", "link": "/api/v1/teams/17"}, "primaryPosition": {"code": "D", "name": "Defenseman", "type": "Defenseman", "abbreviation": "D"}}, "jerseyNumber": "23", "position": {"code": "N/A", "name": "Unknown", "type": "Unknown", "abbreviation": "N/A"}, "stats": {}}, "ID8468083": {"person": {"id": 8468083, "fullName": "Henrik Zetterberg", "link": "/api/v1/people/8468083", "firstName": "Henrik", "lastName": "Zetterberg", "primaryNumber": "40", "birthDate": "1980-10-09", "currentAge": 38, "birthCity": "Njurunda", "birthCountry": "SWE", "nationality": "SWE", "height": "6' 0\"", "weight": 197, "active": true, "alternateCaptain": false, "captain": true, "rookie": false, "shootsCatches": "L", "rosterStatus": "Y", "currentTeam": {"id": 17, "name": "Detroit Red Wings", "link": "/api/v1/teams/17"}, "primaryPosition": {"code": "L", "name": "Left Wing", "type": "Forward", "abbreviation": "LW"}}, "jerseyNumber": "40", "position": {"code": "L", "name": "Left Wing", "type": "Forward", "abbreviation": "LW"}, "stats": {"skaterStats": {"timeOnIce": "19:52", "assists": 0, "goals": 1, "shots": 2, "hits": 0, "powerPlayGoals": 0, "powerPlayAssists": 0, "penaltyMinutes": 2, "faceOffPct": 50.0, "faceOffWins": 7, "faceoffTaken": 14, "takeaways": 1, "giveaways": 0, "shortHandedGoals": 0, "shortHandedAssists": 0, "blocked": 1, "plusMinus": 0, "evenTimeOnIce": "17:46", "powerPlayTimeOnIce": "2:06", "shortHandedTimeOnIce": "0:00"}}}, "ID8477931": {"person": {"id": 8477931, "fullName": "Tomas Nosek", "link": "/api/v1/people/8477931", "firstName": "Tomas", "lastName": "Nosek", "primaryNumber": "92", "birthDate": "1992-09-01", "currentAge": 26, "birthCity": "Pardubice", "birthCountry": "CZE", "nationality": "CZE", "height": "6' 3\"", "weight": 210, "active": true, "alternateCaptain": false, "captain": false, "rookie": true, "shootsCatches": "L", "rosterStatus": "Y", "currentTeam": {"id": 54, "name": "Vegas Golden Knights", "link": "/api/v1/teams/54"}, "primaryPosition": {"code": "L", "name": "Left Wing", "type": "Forward", "abbreviation": "LW"}}, "jerseyNumber": "92", "position": {"code": "N/A", "name": "Unknown", "type": "Unknown", "abbreviation": "N/A"}, "stats": {}}, "ID8476822": {"person": {"id": 8476822, "fullName": "Luke Glendening", "link": "/api/v1/people/8476822", "firstName": "Luke", "lastName": "Glendening", "primaryNumber": "41", "birthDate": "1989-04-28", "currentAge": 29, "birthCity": "Grand Rapids", "birthStateProvince": "MI", "birthCountry": "USA", "nationality": "USA", "height": "5' 11\"", "weight": 199, "active": true, "alternateCaptain": false, "captain": false, "rookie": false, "shootsCatches": "R", "rosterStatus": "Y", "currentTeam": {"id": 17, "name": "Detroit Red Wings", "link": "/api/v1/teams/17"}, "primaryPosition": {"code": "C", "name": "Center", "type": "Forward", "abbreviation": "C"}}, "jerseyNumber": "41", "position": {"code": "C", "name": "Center", "type": "Forward", "abbreviation": "C"}, "stats": {"skaterStats": {"timeOnIce": "13:58", "assists": 0, "goals": 0, "shots": 4, "hits": 1, "powerPlayGoals": 0, "powerPlayAssists": 0, "penaltyMinutes": 0, "faceOffPct": 42.86, "faceOffWins": 3, "faceoffTaken": 7, "takeaways": 1, "giveaways": 0, "shortHandedGoals": 0, "shortHandedAssists": 0, "blocked": 4, "plusMinus": -1, "evenTimeOnIce": "11:18", "powerPlayTimeOnIce": "0:06", "shortHandedTimeOnIce": "2:34"}}}, "ID8470598": {"person": {"id": 8470598, "fullName": "Thomas Vanek", "link": "/api/v1/people/8470598", "firstName": "Thomas", "lastName": "Vanek", "primaryNumber": "26", "birthDate": "1984-01-19", "currentAge": 35, "birthCity": "Vienna", "birthCountry": "AUT", "nationality": "AUT", "height": "6' 2\"", "weight": 214, "active": true, "alternateCaptain": false, "captain": false, "rookie": false, "shootsCatches": "R", "rosterStatus": "Y", "currentTeam": {"id": 23, "name": "Vancouver Canucks", "link": "/api/v1/teams/23"}, "primaryPosition": {"code": "L", "name": "Left Wing", "type": "Forward", "abbreviation": "LW"}}, "jerseyNumber": "62", "position": {"code": "L", "name": "Left Wing", "type": "Forward", "abbreviation": "LW"}, "stats": {"skaterStats": {"timeOnIce": "17:03", "assists": 1, "goals": 0, "shots": 3, "hits": 1, "powerPlayGoals": 0, "powerPlayAssists": 0, "penaltyMinutes": 0, "faceOffPct": 0.0, "faceOffWins": 0, "faceoffTaken": 1, "takeaways": 0, "giveaways": 0, "shortHandedGoals": 0, "shortHandedAssists": 0, "blocked": 0, "plusMinus": -1, "evenTimeOnIce": "15:24", "powerPlayTimeOnIce": "1:39", "shortHandedTimeOnIce": "0:00"}}}, "ID8475772": {"person": {"id": 8475772, "fullName": "Riley Sheahan", "link": "/api/v1/people/8475772", "firstName": "Riley", "lastName": "Sheahan", "primaryNumber": "15", "birthDate": "1991-12-07", "currentAge": 27, "birthCity": "St. Catharines", "birthStateProvince": "ON", "birthCountry": "CAN", "nationality": "CAN", "height": "6' 3\"", "weight": 226, "active": true, "alternateCaptain": false, "captain": false, "rookie": false, "shootsCatches": "L", "rosterStatus": "Y", "currentTeam": {"id": 17, "name": "Detroit Red Wings", "link": "/api/v1/teams/17"}, "primaryPosition": {"code": "C", "name": "Center", "type": "Forward", "abbreviation": "C"}}, "jerseyNumber": "15", "position": {"code": "C", "name": "Center", "type": "Forward", "abbreviation": "C"}, "stats": {"skaterStats": {"timeOnIce": "11:36", "assists": 1, "goals": 0, "shots": 2, "hits": 2, "powerPlayGoals": 0, "powerPlayAssists": 0, "penaltyMinutes": 0, "faceOffPct": 75.0, "faceOffWins": 6, "faceoffTaken": 8, "takeaways": 0, "giveaways": 0, "shortHandedGoals": 0, "shortHandedAssists": 0, "blocked": 1, "plusMinus": -1, "evenTimeOnIce": "9:53", "powerPlayTimeOnIce": "0:17", "shortHandedTimeOnIce": "1:26"}}}, "ID8476443": {"person": {"id": 8476443, "fullName": "Xavier Ouellet", "link": "/api/v1/people/8476443", "firstName": "Xavier", "lastName": "Ouellet", "primaryNumber": "61", "birthDate": "1993-07-29", "currentAge": 25, "birthCity": "Bayonne", "birthCountry": "FRA", "nationality": "FRA", "height": "6' 1\"", "weight": 208, "active": true, "alternateCaptain": false, "captain": false, "rookie": true, "shootsCatches": "L", "rosterStatus": "Y", "currentTeam": {"id": 17, "name": "Detroit Red Wings", "link": "/api/v1/teams/17"}, "primaryPosition": {"code": "D", "name": "Defenseman", "type": "Defenseman", "abbreviation": "D"}}, "jerseyNumber": "61", "position": {"code": "D", "name": "Defenseman", "type": "Defenseman", "abbreviation": "D"}, "stats": {"skaterStats": {"timeOnIce": "19:20", "assists": 0, "goals": 0, "shots": 0, "hits": 1, "powerPlayGoals": 0, "powerPlayAssists": 0, "penaltyMinutes": 0, "faceOffWins": 0, "faceoffTaken": 0, "takeaways": 1, "giveaways": 0, "shortHandedGoals": 0, "shortHandedAssists": 0, "blocked": 2, "plusMinus": 0, "evenTimeOnIce": "17:27", "powerPlayTimeOnIce": "0:06", "shortHandedTimeOnIce": "1:47"}}}, "ID8477215": {"person": {"id": 8477215, "fullName": "Danny DeKeyser", "link": "/api/v1/people/8477215", "firstName": "Danny", "lastName": "DeKeyser", "primaryNumber": "65", "birthDate": "1990-03-07", "currentAge": 29, "birthCity": "Detroit", "birthStateProvince": "MI", "birthCountry": "USA", "nationality": "USA", "height": "6' 3\"", "weight": 192, "active": true, "alternateCaptain": false, "captain": false, "rookie": false, "shootsCatches": "L", "rosterStatus": "Y", "currentTeam": {"id": 17, "name": "Detroit Red Wings", "link": "/api/v1/teams/17"}, "primaryPosition": {"code": "D", "name": "Defenseman", "type": "Defenseman", "abbreviation": "D"}}, "jerseyNumber": "65", "position": {"code": "D", "name": "Defenseman", "type": "Defenseman", "abbreviation": "D"}, "stats": {"skaterStats": {"timeOnIce": "23:48", "assists": 1, "goals": 0, "shots": 0, "hits": 1, "powerPlayGoals": 0, "powerPlayAssists": 0, "penaltyMinutes": 0, "faceOffWins": 0, "faceoffTaken": 0, "takeaways": 2, "giveaways": 0, "shortHandedGoals": 0, "shortHandedAssists": 0, "blocked": 1, "plusMinus": 1, "evenTimeOnIce": "21:22", "powerPlayTimeOnIce": "0:27", "shortHandedTimeOnIce": "1:59"}}}, "ID8477511": {"person": {"id": 8477511, "fullName": "Anthony Mantha", "link": "/api/v1/people/8477511", "firstName": "Anthony", "lastName": "Mantha", "primaryNumber": "39", "birthDate": "1994-09-16", "currentAge": 24, "birthCity": "Longueuil", "birthStateProvince": "QC", "birthCountry": "CAN", "nationality": "CAN", "height": "6' 5\"", "weight": 221, "active": true, "alternateCaptain": false, "captain": false, "rookie": true, "shootsCatches": "L", "rosterStatus": "Y", "currentTeam": {"id": 17, "name": "Detroit Red Wings", "link": "/api/v1/teams/17"}, "primaryPosition": {"code": "R", "name": "Right Wing", "type": "Forward", "abbreviation": "RW"}}, "jerseyNumber": "39", "position": {"code": "R", "name": "Right Wing", "type": "Forward", "abbreviation": "RW"}, "stats": {"skaterStats": {"timeOnIce": "19:35", "assists": 1, "goals": 0, "shots": 2, "hits": 1, "powerPlayGoals": 0, "powerPlayAssists": 0, "penaltyMinutes": 0, "faceOffWins": 0, "faceoffTaken": 0, "takeaways": 1, "giveaways": 0, "shortHandedGoals": 0, "shortHandedAssists": 0, "blocked": 0, "plusMinus": 0, "evenTimeOnIce": "17:20", "powerPlayTimeOnIce": "2:15", "shortHandedTimeOnIce": "0:00"}}}, "ID8477225": {"person": {"id": 8477225, "fullName": "Jared Coreau", "link": "/api/v1/people/8477225", "firstName": "Jared", "lastName": "Coreau", "primaryNumber": "31", "birthDate": "1991-11-05", "currentAge": 27, "birthCity": "Perth", "birthStateProvince": "ON", "birthCountry": "CAN", "nationality": "CAN", "height": "6' 6\"", "weight": 220, "active": true, "alternateCaptain": false, "captain": false, "rookie": true, "shootsCatches": "L", "rosterStatus": "N", "currentTeam": {"id": 17, "name": "Detroit Red Wings", "link": "/api/v1/teams/17"}, "primaryPosition": {"code": "G", "name": "Goalie", "type": "Goalie", "abbreviation": "G"}}, "jerseyNumber": "31", "position": {"code": "G", "name": "Goalie", "type": "Goalie", "abbreviation": "G"}, "stats": {"goalieStats": {"timeOnIce": "58:24", "assists": 0, "goals": 0, "pim": 0, "shots": 36, "saves": 32, "powerPlaySaves": 3, "shortHandedSaves": 1, "evenSaves": 28, "shortHandedShotsAgainst": 1, "evenShotsAgainst": 32, "powerPlayShotsAgainst": 3, "decision": "L", "savePercentage": 88.88888888888889, "powerPlaySavePercentage": 100.0, "shortHandedSavePercentage": 100.0, "evenStrengthSavePercentage": 87.5}}}, "ID8471242": {"person": {"id": 8471242, "fullName": "Mike Green", "link": "/api/v1/people/8471242", "firstName": "Mike", "lastName": "Green", "primaryNumber": "25", "birthDate": "1985-10-12", "currentAge": 33, "birthCity": "Calgary", "birthStateProvince": "AB", "birthCountry": "CAN", "nationality": "CAN", "height": "6' 1\"", "weight": 207, "active": true, "alternateCaptain": false, "captain": false, "rookie": false, "shootsCatches": "R", "rosterStatus": "Y", "currentTeam": {"id": 17, "name": "Detroit Red Wings", "link": "/api/v1/teams/17"}, "primaryPosition": {"code": "D", "name": "Defenseman", "type": "Defenseman", "abbreviation": "D"}}, "jerseyNumber": "25", "position": {"code": "D", "name": "Defenseman", "type": "Defenseman", "abbreviation": "D"}, "stats": {"skaterStats": {"timeOnIce": "24:24", "assists": 1, "goals": 0, "shots": 1, "hits": 1, "powerPlayGoals": 0, "powerPlayAssists": 0, "penaltyMinutes": 0, "faceOffWins": 0, "faceoffTaken": 0, "takeaways": 1, "giveaways": 1, "shortHandedGoals": 0, "shortHandedAssists": 0, "blocked": 0, "plusMinus": 1, "evenTimeOnIce": "21:27", "powerPlayTimeOnIce": "1:56", "shortHandedTimeOnIce": "1:01"}}}, "ID8476450": {"person": {"id": 8476450, "fullName": "Ryan Sproul", "link": "/api/v1/people/8476450", "firstName": "Ryan", "lastName": "Sproul", "primaryNumber": "62", "birthDate": "1993-01-13", "currentAge": 26, "birthCity": "Mississauga", "birthStateProvince": "ON", "birthCountry": "CAN", "nationality": "CAN", "height": "6' 4\"", "weight": 211, "active": true, "alternateCaptain": false, "captain": false, "rookie": true, "shootsCatches": "R", "rosterStatus": "Y", "currentTeam": {"id": 17, "name": "Detroit Red Wings", "link": "/api/v1/teams/17"}, "primaryPosition": {"code": "D", "name": "Defenseman", "type": "Defenseman", "abbreviation": "D"}}, "jerseyNumber": "48", "position": {"code": "D", "name": "Defenseman", "type": "Defenseman", "abbreviation": "D"}, "stats": {"skaterStats": {"timeOnIce": "15:07", "assists": 0, "goals": 0, "shots": 3, "hits": 0, "powerPlayGoals": 0, "powerPlayAssists": 0, "penaltyMinutes": 0, "faceOffWins": 0, "faceoffTaken": 0, "takeaways": 0, "giveaways": 0, "shortHandedGoals": 0, "shortHandedAssists": 0, "blocked": 1, "plusMinus": -3, "evenTimeOnIce": "12:41", "powerPlayTimeOnIce": "2:12", "shortHandedTimeOnIce": "0:14"}}}, "ID8476430": {"person": {"id": 8476430, "fullName": "Tomas Jurco", "link": "/api/v1/people/8476430", "firstName": "Tomas", "lastName": "Jurco", "primaryNumber": "13", "birthDate": "1992-12-28", "currentAge": 26, "birthCity": "Kosice", "birthCountry": "SVK", "nationality": "SVK", "height": "6' 2\"", "weight": 188, "active": true, "alternateCaptain": false, "captain": false, "rookie": false, "shootsCatches": "L", "rosterStatus": "Y", "currentTeam": {"id": 16, "name": "Chicago Blackhawks", "link": "/api/v1/teams/16"}, "primaryPosition": {"code": "L", "name": "Left Wing", "type": "Forward", "abbreviation": "LW"}}, "jerseyNumber": "26", "position": {"code": "L", "name": "Left Wing", "type": "Forward", "abbreviation": "LW"}, "stats": {"skaterStats": {"timeOnIce": "13:44", "assists": 0, "goals": 0, "shots": 2, "hits": 0, "powerPlayGoals": 0, "powerPlayAssists": 0, "penaltyMinutes": 0, "faceOffWins": 0, "faceoffTaken": 0, "takeaways": 0, "giveaways": 0, "shortHandedGoals": 0, "shortHandedAssists": 0, "blocked": 0, "plusMinus": -1, "evenTimeOnIce": "13:38", "powerPlayTimeOnIce": "0:06", "shortHandedTimeOnIce": "0:00"}}}, "ID8475193": {"person": {"id": 8475193, "fullName": "Tomas Tatar", "link": "/api/v1/people/8475193", "firstName": "Tomas", "lastName": "Tatar", "primaryNumber": "21", "birthDate": "1990-12-01", "currentAge": 28, "birthCity": "Ilava", "birthCountry": "SVK", "nationality": "SVK", "height": "5' 10\"", "weight": 185, "active": true, "alternateCaptain": false, "captain": false, "rookie": false, "shootsCatches": "L", "rosterStatus": "Y", "currentTeam": {"id": 17, "name": "Detroit Red Wings", "link": "/api/v1/teams/17"}, "primaryPosition": {"code": "L", "name": "Left Wing", "type": "Forward", "abbreviation": "LW"}}, "jerseyNumber": "21", "position": {"code": "L", "name": "Left Wing", "type": "Forward", "abbreviation": "LW"}, "stats": {"skaterStats": {"timeOnIce": "17:16", "assists": 1, "goals": 0, "shots": 2, "hits": 3, "powerPlayGoals": 0, "powerPlayAssists": 0, "penaltyMinutes": 0, "faceOffWins": 0, "faceoffTaken": 0, "takeaways": 0, "giveaways": 0, "shortHandedGoals": 0, "shortHandedAssists": 0, "blocked": 0, "plusMinus": 0, "evenTimeOnIce": "15:26", "powerPlayTimeOnIce": "1:50", "shortHandedTimeOnIce": "0:00"}}}, "ID8468509": {"person": {"id": 8468509, "fullName": "Niklas Kronwall", "link": "/api/v1/people/8468509", "firstName": "Niklas", "lastName": "Kronwall", "primaryNumber": "55", "birthDate": "1981-01-12", "currentAge": 38, "birthCity": "Stockholm", "birthCountry": "SWE", "nationality": "SWE", "height": "6' 0\"", "weight": 194, "active": true, "alternateCaptain": true, "captain": false, "rookie": false, "shootsCatches": "L", "rosterStatus": "Y", "currentTeam": {"id": 17, "name": "Detroit Red Wings", "link": "/api/v1/teams/17"}, "primaryPosition": {"code": "D", "name": "Defenseman", "type": "Defenseman", "abbreviation": "D"}}, "jerseyNumber": "55", "position": {"code": "D", "name": "Defenseman", "type": "Defenseman", "abbreviation": "D"}, "stats": {"skaterStats": {"timeOnIce": "19:30", "assists": 0, "goals": 0, "shots": 1, "hits": 3, "powerPlayGoals": 0, "powerPlayAssists": 0, "penaltyMinutes": 0, "faceOffWins": 0, "faceoffTaken": 0, "takeaways": 0, "giveaways": 0, "shortHandedGoals": 0, "shortHandedAssists": 0, "blocked": 0, "plusMinus": -1, "evenTimeOnIce": "15:55", "powerPlayTimeOnIce": "1:48", "shortHandedTimeOnIce": "1:47"}}}, "ID8468505": {"person": {"id": 8468505, "fullName": "Steve Ott", "link": "/api/v1/people/8468505", "firstName": "Steve", "lastName": "Ott", "primaryNumber": "92", "birthDate": "1982-08-19", "birthCity": "Summerside", "birthStateProvince": "PE", "birthCountry": "CAN", "nationality": "CAN", "height": "6' 0\"", "weight": 193, "active": false, "rookie": false, "shootsCatches": "L", "rosterStatus": "Y", "primaryPosition": {"code": "C", "name": "Center", "type": "Forward", "abbreviation": "C"}}, "jerseyNumber": "29", "position": {"code": "C", "name": "Center", "type": "Forward", "abbreviation": "C"}, "stats": {"skaterStats": {"timeOnIce": "10:17", "assists": 0, "goals": 0, "shots": 1, "hits": 3, "powerPlayGoals": 0, "powerPlayAssists": 0, "penaltyMinutes": 0, "faceOffPct": 0.0, "faceOffWins": 0, "faceoffTaken": 2, "takeaways": 0, "giveaways": 0, "shortHandedGoals": 0, "shortHandedAssists": 0, "blocked": 2, "plusMinus": -2, "evenTimeOnIce": "7:55", "powerPlayTimeOnIce": "0:00", "shortHandedTimeOnIce": "2:22"}}}}, "goalies": [8477225], "skaters": [8474679, 8475772, 8470778, 8475193, 8471242, 8476430, 8468505, 8477511, 8468083, 8476822, 8476450, 8470144, 8470318, 8468509, 8476443, 8470598, 8477215, 8477946, 8474873, 8477931], "onIce": [8468505, 8470778, 8475772, 8476443, 8476450, 8477225], "onIcePlus": [{"playerId": 8476450, "shiftDuration": 41, "stamina": 66}, {"playerId": 8470778, "shiftDuration": 41, "stamina": 66}, {"playerId": 8477225, "shiftDuration": 41, "stamina": 66}, {"playerId": 8476443, "shiftDuration": 41, "stamina": 66}, {"playerId": 8475772, "shiftDuration": 41, "stamina": 66}, {"playerId": 8468505, "shiftDuration": 41, "stamina": 66}], "scratches": [8474873, 8477931], "penaltyBox": [], "coaches": [{"person": {"fullName": "Jeff Blashill", "link": "/api/v1/people/null"}, "position": {"code": "HC", "name": "Head Coach", "type": "Head Coach", "abbreviation": "Head Coach"}}]}, "home": {"team": {"id": 5, "name": "Pittsburgh Penguins", "link": "/api/v1/teams/5"}, "teamStats": {"teamSkaterStats": {"goals": 5, "pim": 4, "shots": 37, "powerPlayPercentage": "0.0", "powerPlayGoals": 0.0, "powerPlayOpportunities": 2.0, "faceOffWinPercentage": "47.3", "blocked": 13, "takeaways": 2, "giveaways": 12, "hits": 26}}, "players": {"ID8471724": {"person": {"id": 8471724, "fullName": "Kris Letang", "link": "/api/v1/people/8471724", "firstName": "Kris", "lastName": "Letang", "primaryNumber": "58", "birthDate": "1987-04-24", "currentAge": 31, "birthCity": "Montreal", "birthStateProvince": "QC", "birthCountry": "CAN", "nationality": "CAN", "height": "6' 0\"", "weight": 201, "active": true, "alternateCaptain": false, "captain": false, "rookie": false, "shootsCatches": "R", "rosterStatus": "I", "currentTeam": {"id": 5, "name": "Pittsburgh Penguins", "link": "/api/v1/teams/5"}, "primaryPosition": {"code": "D", "name": "Defenseman", "type": "Defenseman", "abbreviation": "D"}}, "jerseyNumber": "58", "position": {"code": "D", "name": "Defenseman", "type": "Defenseman", "abbreviation": "D"}, "stats": {"skaterStats": {"timeOnIce": "24:12", "assists": 1, "goals": 0, "shots": 2, "hits": 3, "powerPlayGoals": 0, "powerPlayAssists": 0, "penaltyMinutes": 0, "faceOffWins": 0, "faceoffTaken": 0, "takeaways": 0, "giveaways": 4, "shortHandedGoals": 0, "shortHandedAssists": 0, "blocked": 3, "plusMinus": 0, "evenTimeOnIce": "19:22", "powerPlayTimeOnIce": "3:10", "shortHandedTimeOnIce": "1:40"}}}, "ID8474602": {"person": {"id": 8474602, "fullName": "Justin Schultz", "link": "/api/v1/people/8474602", "firstName": "Justin", "lastName": "Schultz", "primaryNumber": "4", "birthDate": "1990-07-06", "currentAge": 28, "birthCity": "Kelowna", "birthStateProvince": "BC", "birthCountry": "CAN", "nationality": "CAN", "height": "6' 2\"", "weight": 193, "active": true, "alternateCaptain": false, "captain": false, "rookie": false, "shootsCatches": "R", "rosterStatus": "Y", "currentTeam": {"id": 5, "name": "Pittsburgh Penguins", "link": "/api/v1/teams/5"}, "primaryPosition": {"code": "D", "name": "Defenseman", "type": "Defenseman", "abbreviation": "D"}}, "jerseyNumber": "4", "position": {"code": "D", "name": "Defenseman", "type": "Defenseman", "abbreviation": "D"}, "stats": {"skaterStats": {"timeOnIce": "17:00", "assists": 0, "goals": 1, "shots": 4, "hits": 0, "powerPlayGoals": 0, "powerPlayAssists": 0, "penaltyMinutes": 0, "faceOffWins": 0, "faceoffTaken": 0, "takeaways": 0, "giveaways": 0, "shortHandedGoals": 0, "shortHandedAssists": 0, "blocked": 0, "plusMinus": 1, "evenTimeOnIce": "16:18", "powerPlayTimeOnIce": "0:42", "shortHandedTimeOnIce": "0:00"}}}, "ID8475208": {"person": {"id": 8475208, "fullName": "Brian Dumoulin", "link": "/api/v1/people/8475208", "firstName": "Brian", "lastName": "Dumoulin", "primaryNumber": "8", "birthDate": "1991-09-06", "currentAge": 27, "birthCity": "Biddeford", "birthStateProvince": "ME", "birthCountry": "USA", "nationality": "USA", "height": "6' 4\"", "weight": 207, "active": true, "alternateCaptain": false, "captain": false, "rookie": false, "shootsCatches": "L", "rosterStatus": "Y", "currentTeam": {"id": 5, "name": "Pittsburgh Penguins", "link": "/api/v1/teams/5"}, "primaryPosition": {"code": "D", "name": "Defenseman", "type": "Defenseman", "abbreviation": "D"}}, "jerseyNumber": "8", "position": {"code": "D", "name": "Defenseman", "type": "Defenseman", "abbreviation": "D"}, "stats": {"skaterStats": {"timeOnIce": "19:22", "assists": 0, "goals": 0, "shots": 1, "hits": 2, "powerPlayGoals": 0, "powerPlayAssists": 0, "penaltyMinutes": 0, "faceOffWins": 0, "faceoffTaken": 0, "takeaways": 0, "giveaways": 1, "shortHandedGoals": 0, "shortHandedAssists": 0, "blocked": 0, "plusMinus": 0, "evenTimeOnIce": "18:31", "powerPlayTimeOnIce": "0:00", "shortHandedTimeOnIce": "0:51"}}}, "ID8471675": {"person": {"id": 8471675, "fullName": "Sidney Crosby", "link": "/api/v1/people/8471675", "firstName": "Sidney", "lastName": "Crosby", "primaryNumber": "87", "birthDate": "1987-08-07", "currentAge": 31, "birthCity": "Cole Harbour", "birthStateProvince": "NS", "birthCountry": "CAN", "nationality": "CAN", "height": "5' 11\"", "weight": 200, "active": true, "alternateCaptain": false, "captain": true, "rookie": false, "shootsCatches": "L", "rosterStatus": "Y", "currentTeam": {"id": 5, "name": "Pittsburgh Penguins", "link": "/api/v1/teams/5"}, "primaryPosition": {"code": "C", "name": "Center", "type": "Forward", "abbreviation": "C"}}, "jerseyNumber": "87", "position": {"code": "C", "name": "Center", "type": "Forward", "abbreviation": "C"}, "stats": {"skaterStats": {"timeOnIce": "20:46", "assists": 1, "goals": 0, "shots": 3, "hits": 1, "powerPlayGoals": 0, "powerPlayAssists": 0, "penaltyMinutes": 0, "faceOffPct": 57.14, "faceOffWins": 12, "faceoffTaken": 21, "takeaways": 1, "giveaways": 1, "shortHandedGoals": 0, "shortHandedAssists": 0, "blocked": 0, "plusMinus": 0, "evenTimeOnIce": "17:38", "powerPlayTimeOnIce": "3:08", "shortHandedTimeOnIce": "0:00"}}}, "ID8470110": {"person": {"id": 8470110, "fullName": "Trevor Daley", "link": "/api/v1/people/8470110", "firstName": "Trevor", "lastName": "Daley", "primaryNumber": "83", "birthDate": "1983-10-09", "currentAge": 35, "birthCity": "Toronto", "birthStateProvince": "ON", "birthCountry": "CAN", "nationality": "CAN", "height": "5' 11\"", "weight": 195, "active": true, "alternateCaptain": false, "captain": false, "rookie": false, "shootsCatches": "L", "rosterStatus": "Y", "currentTeam": {"id": 17, "name": "Detroit Red Wings", "link": "/api/v1/teams/17"}, "primaryPosition": {"code": "D", "name": "Defenseman", "type": "Defenseman", "abbreviation": "D"}}, "jerseyNumber": "6", "position": {"code": "D", "name": "Defenseman", "type": "Defenseman", "abbreviation": "D"}, "stats": {"skaterStats": {"timeOnIce": "20:37", "assists": 0, "goals": 0, "shots": 1, "hits": 0, "powerPlayGoals": 0, "powerPlayAssists": 0, "penaltyMinutes": 0, "faceOffWins": 0, "faceoffTaken": 0, "takeaways": 1, "giveaways": 0, "shortHandedGoals": 0, "shortHandedAssists": 0, "blocked": 2, "plusMinus": -1, "evenTimeOnIce": "17:17", "powerPlayTimeOnIce": "1:00", "shortHandedTimeOnIce": "2:20"}}}, "ID8477839": {"person": {"id": 8477839, "fullName": "Conor Sheary", "link": "/api/v1/people/8477839", "firstName": "Conor", "lastName": "Sheary", "primaryNumber": "43", "birthDate": "1992-06-08", "currentAge": 26, "birthCity": "Winchester", "birthStateProvince": "MA", "birthCountry": "USA", "nationality": "USA", "height": "5' 8\"", "weight": 175, "active": true, "alternateCaptain": false, "captain": false, "rookie": false, "shootsCatches": "L", "rosterStatus": "Y", "currentTeam": {"id": 5, "name": "Pittsburgh Penguins", "link": "/api/v1/teams/5"}, "primaryPosition": {"code": "L", "name": "Left Wing", "type": "Forward", "abbreviation": "LW"}}, "jerseyNumber": "43", "position": {"code": "L", "name": "Left Wing", "type": "Forward", "abbreviation": "LW"}, "stats": {"skaterStats": {"timeOnIce": "18:29", "assists": 0, "goals": 0, "shots": 3, "hits": 0, "powerPlayGoals": 0, "powerPlayAssists": 0, "penaltyMinutes": 2, "faceOffWins": 0, "faceoffTaken": 0, "takeaways": 0, "giveaways": 0, "shortHandedGoals": 0, "shortHandedAssists": 0, "blocked": 0, "plusMinus": -2, "evenTimeOnIce": "17:37", "powerPlayTimeOnIce": "0:52", "shortHandedTimeOnIce": "0:00"}}}, "ID8470594": {"person": {"id": 8470594, "fullName": "Marc-Andre Fleury", "link": "/api/v1/people/8470594", "firstName": "Marc-Andre", "lastName": "Fleury", "primaryNumber": "29", "birthDate": "1984-11-28", "currentAge": 34, "birthCity": "Sorel", "birthStateProvince": "QC", "birthCountry": "CAN", "nationality": "CAN", "height": "6' 2\"", "weight": 180, "active": true, "alternateCaptain": false, "captain": false, "rookie": false, "shootsCatches": "L", "rosterStatus": "Y", "currentTeam": {"id": 54, "name": "Vegas Golden Knights", "link": "/api/v1/teams/54"}, "primaryPosition": {"code": "G", "name": "Goalie", "type": "Goalie", "abbreviation": "G"}}, "jerseyNumber": "29", "position": {"code": "G", "name": "Goalie", "type": "Goalie", "abbreviation": "G"}, "stats": {"goalieStats": {"timeOnIce": "59:32", "assists": 0, "goals": 0, "pim": 0, "shots": 31, "saves": 28, "powerPlaySaves": 4, "shortHandedSaves": 1, "evenSaves": 23, "shortHandedShotsAgainst": 1, "evenShotsAgainst": 26, "powerPlayShotsAgainst": 4, "decision": "W", "savePercentage": 90.32258064516128, "powerPlaySavePercentage": 100.0, "shortHandedSavePercentage": 100.0, "evenStrengthSavePercentage": 88.46153846153845}}}, "ID8470611": {"person": {"id": 8470611, "fullName": "Eric Fehr", "link": "/api/v1/people/8470611", "firstName": "Eric", "lastName": "Fehr", "primaryNumber": "23", "birthDate": "1985-09-07", "currentAge": 33, "birthCity": "Winkler", "birthStateProvince": "MB", "birthCountry": "CAN", "nationality": "CAN", "height": "6' 4\"", "weight": 212, "active": true, "alternateCaptain": false, "captain": false, "rookie": false, "shootsCatches": "R", "rosterStatus": "Y", "currentTeam": {"id": 10, "name": "Toronto Maple Leafs", "link": "/api/v1/teams/10"}, "primaryPosition": {"code": "C", "name": "Center", "type": "Forward", "abbreviation": "C"}}, "jerseyNumber": "16", "position": {"code": "C", "name": "Center", "type": "Forward", "abbreviation": "C"}, "stats": {"skaterStats": {"timeOnIce": "10:00", "assists": 0, "goals": 0, "shots": 1, "hits": 1, "powerPlayGoals": 0, "powerPlayAssists": 0, "penaltyMinutes": 0, "faceOffWins": 0, "faceoffTaken": 0, "takeaways": 0, "giveaways": 0, "shortHandedGoals": 0, "shortHandedAssists": 0, "blocked": 0, "plusMinus": 1, "evenTimeOnIce": "9:23", "powerPlayTimeOnIce": "0:00", "shortHandedTimeOnIce": "0:37"}}}, "ID8471887": {"person": {"id": 8471887, "fullName": "Patric Hornqvist", "link": "/api/v1/people/8471887", "firstName": "Patric", "lastName": "Hornqvist", "primaryNumber": "72", "birthDate": "1987-01-01", "currentAge": 32, "birthCity": "Sollentuna", "birthCountry": "SWE", "nationality": "SWE", "height": "5' 11\"", "weight": 189, "active": true, "alternateCaptain": false, "captain": false, "rookie": false, "shootsCatches": "R", "rosterStatus": "Y", "currentTeam": {"id": 5, "name": "Pittsburgh Penguins", "link": "/api/v1/teams/5"}, "primaryPosition": {"code": "R", "name": "Right Wing", "type": "Forward", "abbreviation": "RW"}}, "jerseyNumber": "72", "position": {"code": "R", "name": "Right Wing", "type": "Forward", "abbreviation": "RW"}, "stats": {"skaterStats": {"timeOnIce": "18:38", "assists": 1, "goals": 0, "shots": 1, "hits": 6, "powerPlayGoals": 0, "powerPlayAssists": 0, "penaltyMinutes": 0, "faceOffWins": 0, "faceoffTaken": 0, "takeaways": 0, "giveaways": 1, "shortHandedGoals": 0, "shortHandedAssists": 0, "blocked": 1, "plusMinus": 0, "evenTimeOnIce": "15:58", "powerPlayTimeOnIce": "2:40", "shortHandedTimeOnIce": "0:00"}}}, "ID8477404": {"person": {"id": 8477404, "fullName": "Jake Guentzel", "link": "/api/v1/people/8477404", "firstName": "Jake", "lastName": "Guentzel", "primaryNumber": "59", "birthDate": "1994-10-06", "currentAge": 24, "birthCity": "Omaha", "birthStateProvince": "NE", "birthCountry": "USA", "nationality": "USA", "height": "5' 11\"", "weight": 180, "active": true, "alternateCaptain": false, "captain": false, "rookie": true, "shootsCatches": "L", "rosterStatus": "Y", "currentTeam": {"id": 5, "name": "Pittsburgh Penguins", "link": "/api/v1/teams/5"}, "primaryPosition": {"code": "C", "name": "Center", "type": "Forward", "abbreviation": "C"}}, "jerseyNumber": "59", "position": {"code": "N/A", "name": "Unknown", "type": "Unknown", "abbreviation": "N/A"}, "stats": {}}, "ID8473548": {"person": {"id": 8473548, "fullName": "Phil Kessel", "link": "/api/v1/people/8473548", "firstName": "Phil", "lastName": "Kessel", "primaryNumber": "81", "birthDate": "1987-10-02", "currentAge": 31, "birthCity": "Madison", "birthStateProvince": "WI", "birthCountry": "USA", "nationality": "USA", "height": "6' 0\"", "weight": 202, "active": true, "alternateCaptain": false, "captain": false, "rookie": false, "shootsCatches": "R", "rosterStatus": "Y", "currentTeam": {"id": 5, "name": "Pittsburgh Penguins", "link": "/api/v1/teams/5"}, "primaryPosition": {"code": "R", "name": "Right Wing", "type": "Forward", "abbreviation": "RW"}}, "jerseyNumber": "81", "position": {"code": "R", "name": "Right Wing", "type": "Forward", "abbreviation": "RW"}, "stats": {"skaterStats": {"timeOnIce": "17:30", "assists": 0, "goals": 2, "shots": 4, "hits": 0, "powerPlayGoals": 0, "powerPlayAssists": 0, "penaltyMinutes": 0, "faceOffWins": 0, "faceoffTaken": 0, "takeaways": 0, "giveaways": 2, "shortHandedGoals": 0, "shortHandedAssists": 0, "blocked": 0, "plusMinus": 2, "evenTimeOnIce": "14:22", "powerPlayTimeOnIce": "3:08", "shortHandedTimeOnIce": "0:00"}}}, "ID8474009": {"person": {"id": 8474009, "fullName": "Nick Bonino", "link": "/api/v1/people/8474009", "firstName": "Nick", "lastName": "Bonino", "primaryNumber": "13", "birthDate": "1988-04-20", "currentAge": 30, "birthCity": "Hartford", "birthStateProvince": "CT", "birthCountry": "USA", "nationality": "USA", "height": "6' 1\"", "weight": 196, "active": true, "alternateCaptain": false, "captain": false, "rookie": false, "shootsCatches": "L", "rosterStatus": "Y", "currentTeam": {"id": 18, "name": "Nashville Predators", "link": "/api/v1/teams/18"}, "primaryPosition": {"code": "C", "name": "Center", "type": "Forward", "abbreviation": "C"}}, "jerseyNumber": "13", "position": {"code": "C", "name": "Center", "type": "Forward", "abbreviation": "C"}, "stats": {"skaterStats": {"timeOnIce": "13:36", "assists": 0, "goals": 1, "shots": 1, "hits": 1, "powerPlayGoals": 0, "powerPlayAssists": 0, "penaltyMinutes": 0, "faceOffPct": 40.0, "faceOffWins": 4, "faceoffTaken": 10, "takeaways": 0, "giveaways": 0, "shortHandedGoals": 0, "shortHandedAssists": 0, "blocked": 2, "plusMinus": 0, "evenTimeOnIce": "10:54", "powerPlayTimeOnIce": "0:52", "shortHandedTimeOnIce": "1:50"}}}, "ID8470543": {"person": {"id": 8470543, "fullName": "Chris Kunitz", "link": "/api/v1/people/8470543", "firstName": "Chris", "lastName": "Kunitz", "primaryNumber": "14", "birthDate": "1979-09-26", "currentAge": 39, "birthCity": "Regina", "birthStateProvince": "SK", "birthCountry": "CAN", "nationality": "CAN", "height": "6' 0\"", "weight": 195, "active": true, "alternateCaptain": false, "captain": false, "rookie": false, "shootsCatches": "L", "rosterStatus": "Y", "currentTeam": {"id": 14, "name": "Tampa Bay Lightning", "link": "/api/v1/teams/14"}, "primaryPosition": {"code": "L", "name": "Left Wing", "type": "Forward", "abbreviation": "LW"}}, "jerseyNumber": "14", "position": {"code": "L", "name": "Left Wing", "type": "Forward", "abbreviation": "LW"}, "stats": {"skaterStats": {"timeOnIce": "15:57", "assists": 0, "goals": 0, "shots": 2, "hits": 5, "powerPlayGoals": 0, "powerPlayAssists": 0, "penaltyMinutes": 0, "faceOffWins": 0, "faceoffTaken": 0, "takeaways": 0, "giveaways": 1, "shortHandedGoals": 0, "shortHandedAssists": 0, "blocked": 0, "plusMinus": -1, "evenTimeOnIce": "14:11", "powerPlayTimeOnIce": "1:20", "shortHandedTimeOnIce": "0:26"}}}, "ID8475810": {"person": {"id": 8475810, "fullName": "Bryan Rust", "link": "/api/v1/people/8475810", "firstName": "Bryan", "lastName": "Rust", "primaryNumber": "17", "birthDate": "1992-05-11", "currentAge": 26, "birthCity": "Pontiac", "birthStateProvince": "MI", "birthCountry": "USA", "nationality": "USA", "height": "5' 11\"", "weight": 192, "active": true, "alternateCaptain": false, "captain": false, "rookie": false, "shootsCatches": "R", "rosterStatus": "Y", "currentTeam": {"id": 5, "name": "Pittsburgh Penguins", "link": "/api/v1/teams/5"}, "primaryPosition": {"code": "R", "name": "Right Wing", "type": "Forward", "abbreviation": "RW"}}, "jerseyNumber": "17", "position": {"code": "R", "name": "Right Wing", "type": "Forward", "abbreviation": "RW"}, "stats": {"skaterStats": {"timeOnIce": "12:35", "assists": 1, "goals": 0, "shots": 3, "hits": 2, "powerPlayGoals": 0, "powerPlayAssists": 0, "penaltyMinutes": 0, "faceOffPct": 0.0, "faceOffWins": 0, "faceoffTaken": 2, "takeaways": 0, "giveaways": 0, "shortHandedGoals": 0, "shortHandedAssists": 0, "blocked": 0, "plusMinus": 1, "evenTimeOnIce": "11:28", "powerPlayTimeOnIce": "0:00", "shortHandedTimeOnIce": "1:07"}}}, "ID8475832": {"person": {"id": 8475832, "fullName": "Tom Kuhnhackl", "link": "/api/v1/people/8475832", "firstName": "Tom", "lastName": "Kuhnhackl", "primaryNumber": "34", "birthDate": "1992-01-21", "currentAge": 27, "birthCity": "Landshut", "birthCountry": "DEU", "nationality": "DEU", "height": "6' 2\"", "weight": 196, "active": true, "alternateCaptain": false, "captain": false, "rookie": false, "shootsCatches": "L", "rosterStatus": "Y", "currentTeam": {"id": 5, "name": "Pittsburgh Penguins", "link": "/api/v1/teams/5"}, "primaryPosition": {"code": "R", "name": "Right Wing", "type": "Forward", "abbreviation": "RW"}}, "jerseyNumber": "34", "position": {"code": "N/A", "name": "Unknown", "type": "Unknown", "abbreviation": "N/A"}, "stats": {}}, "ID8471215": {"person": {"id": 8471215, "fullName": "Evgeni Malkin", "link": "/api/v1/people/8471215", "firstName": "Evgeni", "lastName": "Malkin", "primaryNumber": "71", "birthDate": "1986-07-31", "currentAge": 32, "birthCity": "Magnitogorsk", "birthCountry": "RUS", "nationality": "RUS", "height": "6' 3\"", "weight": 195, "active": true, "alternateCaptain": true, "captain": false, "rookie": false, "shootsCatches": "L", "rosterStatus": "Y", "currentTeam": {"id": 5, "name": "Pittsburgh Penguins", "link": "/api/v1/teams/5"}, "primaryPosition": {"code": "C", "name": "Center", "type": "Forward", "abbreviation": "C"}}, "jerseyNumber": "71", "position": {"code": "C", "name": "Center", "type": "Forward", "abbreviation": "C"}, "stats": {"skaterStats": {"timeOnIce": "19:24", "assists": 2, "goals": 0, "shots": 3, "hits": 1, "powerPlayGoals": 0, "powerPlayAssists": 0, "penaltyMinutes": 0, "faceOffPct": 46.15, "faceOffWins": 6, "faceoffTaken": 13, "takeaways": 0, "giveaways": 1, "shortHandedGoals": 0, "shortHandedAssists": 0, "blocked": 0, "plusMinus": 2, "evenTimeOnIce": "15:58", "powerPlayTimeOnIce": "3:08", "shortHandedTimeOnIce": "0:18"}}}, "ID8476874": {"person": {"id": 8476874, "fullName": "Olli Maatta", "link": "/api/v1/people/8476874", "firstName": "Olli", "lastName": "Maatta", "primaryNumber": "3", "birthDate": "1994-08-22", "currentAge": 24, "birthCity": "Jyv\u00e4skyl\u00e4", "birthCountry": "FIN", "nationality": "FIN", "height": "6' 2\"", "weight": 206, "active": true, "alternateCaptain": false, "captain": false, "rookie": false, "shootsCatches": "L", "rosterStatus": "Y", "currentTeam": {"id": 5, "name": "Pittsburgh Penguins", "link": "/api/v1/teams/5"}, "primaryPosition": {"code": "D", "name": "Defenseman", "type": "Defenseman", "abbreviation": "D"}}, "jerseyNumber": "3", "position": {"code": "D", "name": "Defenseman", "type": "Defenseman", "abbreviation": "D"}, "stats": {"skaterStats": {"timeOnIce": "18:41", "assists": 0, "goals": 0, "shots": 1, "hits": 0, "powerPlayGoals": 0, "powerPlayAssists": 0, "penaltyMinutes": 0, "faceOffWins": 0, "faceoffTaken": 0, "takeaways": 0, "giveaways": 0, "shortHandedGoals": 0, "shortHandedAssists": 0, "blocked": 2, "plusMinus": 0, "evenTimeOnIce": "16:13", "powerPlayTimeOnIce": "0:00", "shortHandedTimeOnIce": "2:28"}}}, "ID8474013": {"person": {"id": 8474013, "fullName": "Ian Cole", "link": "/api/v1/people/8474013", "firstName": "Ian", "lastName": "Cole", "primaryNumber": "28", "birthDate": "1989-02-21", "currentAge": 30, "birthCity": "Ann Arbor", "birthStateProvince": "MI", "birthCountry": "USA", "nationality": "USA", "height": "6' 1\"", "weight": 219, "active": true, "alternateCaptain": false, "captain": false, "rookie": false, "shootsCatches": "L", "rosterStatus": "Y", "currentTeam": {"id": 5, "name": "Pittsburgh Penguins", "link": "/api/v1/teams/5"}, "primaryPosition": {"code": "D", "name": "Defenseman", "type": "Defenseman", "abbreviation": "D"}}, "jerseyNumber": "28", "position": {"code": "D", "name": "Defenseman", "type": "Defenseman", "abbreviation": "D"}, "stats": {"skaterStats": {"timeOnIce": "17:02", "assists": 2, "goals": 0, "shots": 2, "hits": 2, "powerPlayGoals": 0, "powerPlayAssists": 0, "penaltyMinutes": 2, "faceOffWins": 0, "faceoffTaken": 0, "takeaways": 0, "giveaways": 0, "shortHandedGoals": 0, "shortHandedAssists": 0, "blocked": 2, "plusMinus": 3, "evenTimeOnIce": "16:21", "powerPlayTimeOnIce": "0:00", "shortHandedTimeOnIce": "0:41"}}}, "ID8474176": {"person": {"id": 8474176, "fullName": "Carl Hagelin", "link": "/api/v1/people/8474176", "firstName": "Carl", "lastName": "Hagelin", "primaryNumber": "62", "birthDate": "1988-08-23", "currentAge": 30, "birthCity": "Sodertalje", "birthCountry": "SWE", "nationality": "SWE", "height": "5' 11\"", "weight": 186, "active": true, "alternateCaptain": false, "captain": false, "rookie": false, "shootsCatches": "L", "rosterStatus": "Y", "currentTeam": {"id": 5, "name": "Pittsburgh Penguins", "link": "/api/v1/teams/5"}, "primaryPosition": {"code": "L", "name": "Left Wing", "type": "Forward", "abbreviation": "LW"}}, "jerseyNumber": "62", "position": {"code": "L", "name": "Left Wing", "type": "Forward", "abbreviation": "LW"}, "stats": {"skaterStats": {"timeOnIce": "13:58", "assists": 2, "goals": 0, "shots": 2, "hits": 0, "powerPlayGoals": 0, "powerPlayAssists": 0, "penaltyMinutes": 0, "faceOffWins": 0, "faceoffTaken": 0, "takeaways": 0, "giveaways": 1, "shortHandedGoals": 0, "shortHandedAssists": 0, "blocked": 0, "plusMinus": 2, "evenTimeOnIce": "12:08", "powerPlayTimeOnIce": "0:00", "shortHandedTimeOnIce": "1:50"}}}, "ID8464989": {"person": {"id": 8464989, "fullName": "Matt Cullen", "link": "/api/v1/people/8464989", "firstName": "Matt", "lastName": "Cullen", "primaryNumber": "7", "birthDate": "1976-11-02", "currentAge": 42, "birthCity": "Virginia", "birthStateProvince": "MN", "birthCountry": "USA", "nationality": "USA", "height": "6' 1\"", "weight": 200, "active": true, "alternateCaptain": false, "captain": false, "rookie": false, "shootsCatches": "L", "rosterStatus": "Y", "currentTeam": {"id": 30, "name": "Minnesota Wild", "link": "/api/v1/teams/30"}, "primaryPosition": {"code": "C", "name": "Center", "type": "Forward", "abbreviation": "C"}}, "jerseyNumber": "7", "position": {"code": "C", "name": "Center", "type": "Forward", "abbreviation": "C"}, "stats": {"skaterStats": {"timeOnIce": "10:42", "assists": 0, "goals": 1, "shots": 0, "hits": 1, "powerPlayGoals": 0, "powerPlayAssists": 0, "penaltyMinutes": 0, "faceOffPct": 44.44, "faceOffWins": 4, "faceoffTaken": 9, "takeaways": 0, "giveaways": 0, "shortHandedGoals": 0, "shortHandedAssists": 0, "blocked": 0, "plusMinus": 2, "evenTimeOnIce": "8:50", "powerPlayTimeOnIce": "0:00", "shortHandedTimeOnIce": "1:52"}}}, "ID8476293": {"person": {"id": 8476293, "fullName": "Scott Wilson", "link": "/api/v1/people/8476293", "firstName": "Scott", "lastName": "Wilson", "primaryNumber": "23", "birthDate": "1992-04-24", "currentAge": 26, "birthCity": "Oakville", "birthStateProvince": "ON", "birthCountry": "CAN", "nationality": "CAN", "height": "5' 11\"", "weight": 183, "active": true, "alternateCaptain": false, "captain": false, "rookie": true, "shootsCatches": "L", "rosterStatus": "Y", "currentTeam": {"id": 5, "name": "Pittsburgh Penguins", "link": "/api/v1/teams/5"}, "primaryPosition": {"code": "L", "name": "Left Wing", "type": "Forward", "abbreviation": "LW"}}, "jerseyNumber": "23", "position": {"code": "L", "name": "Left Wing", "type": "Forward", "abbreviation": "LW"}, "stats": {"skaterStats": {"timeOnIce": "7:59", "assists": 0, "goals": 0, "shots": 2, "hits": 1, "powerPlayGoals": 0, "powerPlayAssists": 0, "penaltyMinutes": 0, "faceOffWins": 0, "faceoffTaken": 0, "takeaways": 0, "giveaways": 0, "shortHandedGoals": 0, "shortHandedAssists": 0, "blocked": 1, "plusMinus": 1, "evenTimeOnIce": "7:59", "powerPlayTimeOnIce": "0:00", "shortHandedTimeOnIce": "0:00"}}}, "ID8476162": {"person": {"id": 8476162, "fullName": "Steve Oleksy", "link": "/api/v1/people/8476162", "firstName": "Steve", "lastName": "Oleksy", "primaryNumber": "43", "birthDate": "1986-02-04", "currentAge": 33, "birthCity": "Chesterfield", "birthStateProvince": "MI", "birthCountry": "USA", "nationality": "USA", "height": "6' 0\"", "weight": 190, "active": true, "alternateCaptain": false, "captain": false, "rookie": false, "shootsCatches": "R", "rosterStatus": "Y", "currentTeam": {"id": 24, "name": "Anaheim Ducks", "link": "/api/v1/teams/24"}, "primaryPosition": {"code": "D", "name": "Defenseman", "type": "Defenseman", "abbreviation": "D"}}, "jerseyNumber": "43", "position": {"code": "N/A", "name": "Unknown", "type": "Unknown", "abbreviation": "N/A"}, "stats": {}}}, "goalies": [8470594], "skaters": [8476874, 8474602, 8470110, 8464989, 8475208, 8474009, 8470543, 8470611, 8475810, 8476293, 8474013, 8477839, 8471724, 8474176, 8471215, 8471887, 8473548, 8471675, 8477404, 8475832, 8476162], "onIce": [8470110, 8470594, 8470611, 8474009, 8474176, 8476874], "onIcePlus": [{"playerId": 8474176, "shiftDuration": 41, "stamina": 66}, {"playerId": 8470110, "shiftDuration": 41, "stamina": 66}, {"playerId": 8476874, "shiftDuration": 41, "stamina": 66}, {"playerId": 8474009, "shiftDuration": 41, "stamina": 66}, {"playerId": 8470594, "shiftDuration": 812, "stamina": 33}, {"playerId": 8470611, "shiftDuration": 9, "stamina": 100}], "scratches": [8477404, 8475832, 8476162], "penaltyBox": [], "coaches": [{"person": {"fullName": "Mike Sullivan", "link": "/api/v1/people/null"}, "position": {"code": "HC", "name": "Head Coach", "type": "Head Coach", "abbreviation": "Head Coach"}}]}}, "officials": [{"official": {"id": 2459, "fullName": "Justin St. Pierre ", "link": "/api/v1/people/2459"}, "officialType": "Referee"}, {"official": {"id": 2520, "fullName": "Ghislain Hebert", "link": "/api/v1/people/2520"}, "officialType": "Referee"}, {"official": {"id": 2266, "fullName": "Scott Driscoll", "link": "/api/v1/people/2266"}, "officialType": "Linesman"}, {"official": {"id": 2325, "fullName": "Brian Mach", "link": "/api/v1/people/2325"}, "officialType": "Linesman"}]}