{"copyright": "NHL and the NHL Shield are registered trademarks of the National Hockey League. NHL and NHL team marks are the property of the NHL and its teams. \u00a9 NHL 2019. All Rights Reserved.", "teams": {"away": {"team": {"id": 20, "name": "Calgary Flames", "link": "/api/v1/teams/20"}, "teamStats": {"teamSkaterStats": {"goals": 3, "pim": 12, "shots": 23, "powerPlayPercentage": "0.0", "powerPlayGoals": 0.0, "powerPlayOpportunities": 4.0, "faceOffWinPercentage": "49.2", "blocked": 18, "takeaways": 10, "giveaways": 4, "hits": 32}}, "players": {"ID8470966": {"person": {"id": 8470966, "fullName": "Mark Giordano", "link": "/api/v1/people/8470966", "firstName": "Mark", "lastName": "Giordano", "primaryNumber": "5", "birthDate": "1983-10-03", "currentAge": 35, "birthCity": "Toronto", "birthStateProvince": "ON", "birthCountry": "CAN", "nationality": "CAN", "height": "6' 0\"", "weight": 198, "active": true, "alternateCaptain": false, "captain": true, "rookie": false, "shootsCatches": "L", "rosterStatus": "Y", "currentTeam": {"id": 20, "name": "Calgary Flames", "link": "/api/v1/teams/20"}, "primaryPosition": {"code": "D", "name": "Defenseman", "type": "Defenseman", "abbreviation": "D"}}, "jerseyNumber": "5", "position": {"code": "D", "name": "Defenseman", "type": "Defenseman", "abbreviation": "D"}, "stats": {"skaterStats": {"timeOnIce": "26:49", "assists": 0, "goals": 0, "shots": 3, "hits": 1, "powerPlayGoals": 0, "powerPlayAssists": 0, "penaltyMinutes": 0, "faceOffWins": 0, "faceoffTaken": 0, "takeaways": 3, "giveaways": 0, "shortHandedGoals": 0, "shortHandedAssists": 0, "blocked": 1, "plusMinus": 1, "evenTimeOnIce": "16:32", "powerPlayTimeOnIce": "4:44", "shortHandedTimeOnIce": "5:33"}}}, "ID8474628": {"person": {"id": 8474628, "fullName": "Michael Stone", "link": "/api/v1/people/8474628", "firstName": "Michael", "lastName": "Stone", "primaryNumber": "26", "birthDate": "1990-06-07", "currentAge": 28, "birthCity": "Winnipeg", "birthStateProvince": "MB", "birthCountry": "CAN", "nationality": "CAN", "height": "6' 3\"", "weight": 210, "active": true, "alternateCaptain": false, "captain": false, "rookie": false, "shootsCatches": "R", "rosterStatus": "Y", "currentTeam": {"id": 20, "name": "Calgary Flames", "link": "/api/v1/teams/20"}, "primaryPosition": {"code": "D", "name": "Defenseman", "type": "Defenseman", "abbreviation": "D"}}, "jerseyNumber": "26", "position": {"code": "D", "name": "Defenseman", "type": "Defenseman", "abbreviation": "D"}, "stats": {"skaterStats": {"timeOnIce": "14:35", "assists": 1, "goals": 0, "shots": 0, "hits": 3, "powerPlayGoals": 0, "powerPlayAssists": 0, "penaltyMinutes": 0, "faceOffWins": 0, "faceoffTaken": 0, "takeaways": 0, "giveaways": 0, "shortHandedGoals": 0, "shortHandedAssists": 0, "blocked": 3, "plusMinus": 1, "evenTimeOnIce": "10:04", "powerPlayTimeOnIce": "0:00", "shortHandedTimeOnIce": "4:31"}}}, "ID8469608": {"person": {"id": 8469608, "fullName": "Mike Smith", "link": "/api/v1/people/8469608", "firstName": "Mike", "lastName": "Smith", "primaryNumber": "41", "birthDate": "1982-03-22", "currentAge": 37, "birthCity": "Kingston", "birthStateProvince": "ON", "birthCountry": "CAN", "nationality": "CAN", "height": "6' 4\"", "weight": 215, "active": true, "alternateCaptain": false, "captain": false, "rookie": false, "shootsCatches": "L", "rosterStatus": "Y", "currentTeam": {"id": 20, "name": "Calgary Flames", "link": "/api/v1/teams/20"}, "primaryPosition": {"code": "G", "name": "Goalie", "type": "Goalie", "abbreviation": "G"}}, "jerseyNumber": "41", "position": {"code": "G", "name": "Goalie", "type": "Goalie", "abbreviation": "G"}, "stats": {"goalieStats": {"timeOnIce": "60:00", "assists": 0, "goals": 0, "pim": 0, "shots": 36, "saves": 34, "powerPlaySaves": 5, "shortHandedSaves": 1, "evenSaves": 28, "shortHandedShotsAgainst": 1, "evenShotsAgainst": 29, "powerPlayShotsAgainst": 6, "decision": "W", "savePercentage": 94.44444444444444, "powerPlaySavePercentage": 83.33333333333334, "shortHandedSavePercentage": 100.0, "evenStrengthSavePercentage": 96.55172413793103}}}, "ID8474749": {"person": {"id": 8474749, "fullName": "Matt Bartkowski", "link": "/api/v1/people/8474749", "firstName": "Matt", "lastName": "Bartkowski", "primaryNumber": "44", "birthDate": "1988-06-04", "currentAge": 30, "birthCity": "Pittsburgh", "birthStateProvince": "PA", "birthCountry": "USA", "nationality": "USA", "height": "6' 1\"", "weight": 196, "active": true, "alternateCaptain": false, "captain": false, "rookie": false, "shootsCatches": "L", "rosterStatus": "Y", "currentTeam": {"id": 20, "name": "Calgary Flames", "link": "/api/v1/teams/20"}, "primaryPosition": {"code": "D", "name": "Defenseman", "type": "Defenseman", "abbreviation": "D"}}, "jerseyNumber": "44", "position": {"code": "N/A", "name": "Unknown", "type": "Unknown", "abbreviation": "N/A"}, "stats": {}}, "ID8475949": {"person": {"id": 8475949, "fullName": "Marek Hrivik", "link": "/api/v1/people/8475949", "firstName": "Marek", "lastName": "Hrivik", "primaryNumber": "46", "birthDate": "1991-08-28", "currentAge": 27, "birthCity": "Cadca", "birthCountry": "SVK", "nationality": "SVK", "height": "6' 2\"", "weight": 197, "active": true, "alternateCaptain": false, "captain": false, "rookie": false, "shootsCatches": "R", "rosterStatus": "Y", "currentTeam": {"id": 20, "name": "Calgary Flames", "link": "/api/v1/teams/20"}, "primaryPosition": {"code": "L", "name": "Left Wing", "type": "Forward", "abbreviation": "LW"}}, "jerseyNumber": "46", "position": {"code": "N/A", "name": "Unknown", "type": "Unknown", "abbreviation": "N/A"}, "stats": {}}, "ID8475907": {"person": {"id": 8475907, "fullName": "Micheal Ferland", "link": "/api/v1/people/8475907", "firstName": "Micheal", "lastName": "Ferland", "primaryNumber": "79", "birthDate": "1992-04-20", "currentAge": 26, "birthCity": "Swan River", "birthStateProvince": "MB", "birthCountry": "CAN", "nationality": "CAN", "height": "6' 2\"", "weight": 208, "active": true, "alternateCaptain": false, "captain": false, "rookie": false, "shootsCatches": "L", "rosterStatus": "Y", "currentTeam": {"id": 20, "name": "Calgary Flames", "link": "/api/v1/teams/20"}, "primaryPosition": {"code": "L", "name": "Left Wing", "type": "Forward", "abbreviation": "LW"}}, "jerseyNumber": "79", "position": {"code": "L", "name": "Left Wing", "type": "Forward", "abbreviation": "LW"}, "stats": {"skaterStats": {"timeOnIce": "14:01", "assists": 0, "goals": 0, "shots": 0, "hits": 0, "powerPlayGoals": 0, "powerPlayAssists": 0, "penaltyMinutes": 2, "faceOffWins": 0, "faceoffTaken": 0, "takeaways": 0, "giveaways": 0, "shortHandedGoals": 0, "shortHandedAssists": 0, "blocked": 0, "plusMinus": 3, "evenTimeOnIce": "12:53", "powerPlayTimeOnIce": "1:08", "shortHandedTimeOnIce": "0:00"}}}, "ID8477903": {"person": {"id": 8477903, "fullName": "Garnet Hathaway", "link": "/api/v1/people/8477903", "firstName": "Garnet", "lastName": "Hathaway", "primaryNumber": "21", "birthDate": "1991-11-23", "currentAge": 27, "birthCity": "Kennebunkport", "birthStateProvince": "ME", "birthCountry": "USA", "nationality": "USA", "height": "6' 2\"", "weight": 208, "active": true, "alternateCaptain": false, "captain": false, "rookie": false, "shootsCatches": "R", "rosterStatus": "Y", "currentTeam": {"id": 20, "name": "Calgary Flames", "link": "/api/v1/teams/20"}, "primaryPosition": {"code": "R", "name": "Right Wing", "type": "Forward", "abbreviation": "RW"}}, "jerseyNumber": "21", "position": {"code": "R", "name": "Right Wing", "type": "Forward", "abbreviation": "RW"}, "stats": {"skaterStats": {"timeOnIce": "12:47", "assists": 0, "goals": 0, "shots": 0, "hits": 5, "powerPlayGoals": 0, "powerPlayAssists": 0, "penaltyMinutes": 0, "faceOffWins": 0, "faceoffTaken": 0, "takeaways": 0, "giveaways": 0, "shortHandedGoals": 0, "shortHandedAssists": 0, "blocked": 0, "plusMinus": -1, "evenTimeOnIce": "10:01", "powerPlayTimeOnIce": "0:00", "shortHandedTimeOnIce": "2:46"}}}, "ID8476967": {"person": {"id": 8476967, "fullName": "Brett Kulak", "link": "/api/v1/people/8476967", "firstName": "Brett", "lastName": "Kulak", "primaryNumber": "61", "birthDate": "1994-01-06", "currentAge": 25, "birthCity": "Edmonton", "birthStateProvince": "AB", "birthCountry": "CAN", "nationality": "CAN", "height": "6' 2\"", "weight": 187, "active": true, "alternateCaptain": false, "captain": false, "rookie": false, "shootsCatches": "L", "rosterStatus": "Y", "currentTeam": {"id": 20, "name": "Calgary Flames", "link": "/api/v1/teams/20"}, "primaryPosition": {"code": "D", "name": "Defenseman", "type": "Defenseman", "abbreviation": "D"}}, "jerseyNumber": "61", "position": {"code": "D", "name": "Defenseman", "type": "Defenseman", "abbreviation": "D"}, "stats": {"skaterStats": {"timeOnIce": "8:24", "assists": 0, "goals": 0, "shots": 1, "hits": 0, "powerPlayGoals": 0, "powerPlayAssists": 0, "penaltyMinutes": 0, "faceOffWins": 0, "faceoffTaken": 0, "takeaways": 0, "giveaways": 0, "shortHandedGoals": 0, "shortHandedAssists": 0, "blocked": 0, "plusMinus": 0, "evenTimeOnIce": "8:18", "powerPlayTimeOnIce": "0:06", "shortHandedTimeOnIce": "0:00"}}}, "ID8477935": {"person": {"id": 8477935, "fullName": "Sam Bennett", "link": "/api/v1/people/8477935", "firstName": "Sam", "lastName": "Bennett", "primaryNumber": "93", "birthDate": "1996-06-20", "currentAge": 22, "birthCity": "Holland Landing", "birthStateProvince": "ON", "birthCountry": "CAN", "nationality": "CAN", "height": "6' 1\"", "weight": 200, "active": true, "alternateCaptain": false, "captain": false, "rookie": false, "shootsCatches": "L", "rosterStatus": "Y", "currentTeam": {"id": 20, "name": "Calgary Flames", "link": "/api/v1/teams/20"}, "primaryPosition": {"code": "C", "name": "Center", "type": "Forward", "abbreviation": "C"}}, "jerseyNumber": "93", "position": {"code": "C", "name": "Center", "type": "Forward", "abbreviation": "C"}, "stats": {"skaterStats": {"timeOnIce": "9:00", "assists": 0, "goals": 0, "shots": 1, "hits": 3, "powerPlayGoals": 0, "powerPlayAssists": 0, "penaltyMinutes": 4, "faceOffWins": 0, "faceoffTaken": 0, "takeaways": 0, "giveaways": 0, "shortHandedGoals": 0, "shortHandedAssists": 0, "blocked": 0, "plusMinus": -1, "evenTimeOnIce": "8:30", "powerPlayTimeOnIce": "0:30", "shortHandedTimeOnIce": "0:00"}}}, "ID8477508": {"person": {"id": 8477508, "fullName": "Curtis Lazar", "link": "/api/v1/people/8477508", "firstName": "Curtis", "lastName": "Lazar", "primaryNumber": "20", "birthDate": "1995-02-02", "currentAge": 24, "birthCity": "Salmon Arm", "birthStateProvince": "BC", "birthCountry": "CAN", "nationality": "CAN", "height": "6' 0\"", "weight": 209, "active": true, "alternateCaptain": false, "captain": false, "rookie": false, "shootsCatches": "R", "rosterStatus": "Y", "currentTeam": {"id": 20, "name": "Calgary Flames", "link": "/api/v1/teams/20"}, "primaryPosition": {"code": "C", "name": "Center", "type": "Forward", "abbreviation": "C"}}, "jerseyNumber": "20", "position": {"code": "C", "name": "Center", "type": "Forward", "abbreviation": "C"}, "stats": {"skaterStats": {"timeOnIce": "7:17", "assists": 0, "goals": 0, "shots": 1, "hits": 5, "powerPlayGoals": 0, "powerPlayAssists": 0, "penaltyMinutes": 0, "faceOffPct": 33.33, "faceOffWins": 1, "faceoffTaken": 3, "takeaways": 0, "giveaways": 0, "shortHandedGoals": 0, "shortHandedAssists": 0, "blocked": 0, "plusMinus": 0, "evenTimeOnIce": "7:17", "powerPlayTimeOnIce": "0:00", "shortHandedTimeOnIce": "0:00"}}}, "ID8473564": {"person": {"id": 8473564, "fullName": "Michael Frolik", "link": "/api/v1/people/8473564", "firstName": "Michael", "lastName": "Frolik", "primaryNumber": "67", "birthDate": "1988-02-17", "currentAge": 31, "birthCity": "Kladno", "birthCountry": "CZE", "nationality": "CZE", "height": "6' 1\"", "weight": 194, "active": true, "alternateCaptain": false, "captain": false, "rookie": false, "shootsCatches": "L", "rosterStatus": "Y", "currentTeam": {"id": 20, "name": "Calgary Flames", "link": "/api/v1/teams/20"}, "primaryPosition": {"code": "R", "name": "Right Wing", "type": "Forward", "abbreviation": "RW"}}, "jerseyNumber": "67", "position": {"code": "R", "name": "Right Wing", "type": "Forward", "abbreviation": "RW"}, "stats": {"skaterStats": {"timeOnIce": "18:36", "assists": 0, "goals": 0, "shots": 0, "hits": 2, "powerPlayGoals": 0, "powerPlayAssists": 0, "penaltyMinutes": 0, "faceOffPct": 0.0, "faceOffWins": 0, "faceoffTaken": 1, "takeaways": 0, "giveaways": 0, "shortHandedGoals": 0, "shortHandedAssists": 0, "blocked": 0, "plusMinus": 0, "evenTimeOnIce": "14:26", "powerPlayTimeOnIce": "1:08", "shortHandedTimeOnIce": "3:02"}}}, "ID8471426": {"person": {"id": 8471426, "fullName": "Troy Brouwer", "link": "/api/v1/people/8471426", "firstName": "Troy", "lastName": "Brouwer", "primaryNumber": "36", "birthDate": "1985-08-17", "currentAge": 33, "birthCity": "Vancouver", "birthStateProvince": "BC", "birthCountry": "CAN", "nationality": "CAN", "height": "6' 3\"", "weight": 215, "active": true, "alternateCaptain": false, "captain": false, "rookie": false, "shootsCatches": "R", "rosterStatus": "Y", "currentTeam": {"id": 20, "name": "Calgary Flames", "link": "/api/v1/teams/20"}, "primaryPosition": {"code": "R", "name": "Right Wing", "type": "Forward", "abbreviation": "RW"}}, "jerseyNumber": "36", "position": {"code": "R", "name": "Right Wing", "type": "Forward", "abbreviation": "RW"}, "stats": {"skaterStats": {"timeOnIce": "14:50", "assists": 0, "goals": 0, "shots": 0, "hits": 2, "powerPlayGoals": 0, "powerPlayAssists": 0, "penaltyMinutes": 2, "faceOffPct": 33.33, "faceOffWins": 2, "faceoffTaken": 6, "takeaways": 0, "giveaways": 0, "shortHandedGoals": 0, "shortHandedAssists": 0, "blocked": 2, "plusMinus": 0, "evenTimeOnIce": "8:46", "powerPlayTimeOnIce": "2:30", "shortHandedTimeOnIce": "3:34"}}}, "ID8474612": {"person": {"id": 8474612, "fullName": "Travis Hamonic", "link": "/api/v1/people/8474612", "firstName": "Travis", "lastName": "Hamonic", "primaryNumber": "24", "birthDate": "1990-08-16", "currentAge": 28, "birthCity": "St. Malo", "birthStateProvince": "MB", "birthCountry": "CAN", "nationality": "CAN", "height": "6' 2\"", "weight": 205, "active": true, "alternateCaptain": false, "captain": false, "rookie": false, "shootsCatches": "R", "rosterStatus": "Y", "currentTeam": {"id": 20, "name": "Calgary Flames", "link": "/api/v1/teams/20"}, "primaryPosition": {"code": "D", "name": "Defenseman", "type": "Defenseman", "abbreviation": "D"}}, "jerseyNumber": "24", "position": {"code": "D", "name": "Defenseman", "type": "Defenseman", "abbreviation": "D"}, "stats": {"skaterStats": {"timeOnIce": "22:46", "assists": 0, "goals": 0, "shots": 3, "hits": 2, "powerPlayGoals": 0, "powerPlayAssists": 0, "penaltyMinutes": 2, "faceOffWins": 0, "faceoffTaken": 0, "takeaways": 1, "giveaways": 0, "shortHandedGoals": 0, "shortHandedAssists": 0, "blocked": 3, "plusMinus": 0, "evenTimeOnIce": "18:50", "powerPlayTimeOnIce": "0:00", "shortHandedTimeOnIce": "3:56"}}}, "ID8474673": {"person": {"id": 8474673, "fullName": "TJ Brodie", "link": "/api/v1/people/8474673", "firstName": "TJ", "lastName": "Brodie", "primaryNumber": "7", "birthDate": "1990-06-07", "currentAge": 28, "birthCity": "Chatham", "birthStateProvince": "ON", "birthCountry": "CAN", "nationality": "CAN", "height": "6' 1\"", "weight": 182, "active": true, "alternateCaptain": false, "captain": false, "rookie": false, "shootsCatches": "L", "rosterStatus": "Y", "currentTeam": {"id": 20, "name": "Calgary Flames", "link": "/api/v1/teams/20"}, "primaryPosition": {"code": "D", "name": "Defenseman", "type": "Defenseman", "abbreviation": "D"}}, "jerseyNumber": "7", "position": {"code": "D", "name": "Defenseman", "type": "Defenseman", "abbreviation": "D"}, "stats": {"skaterStats": {"timeOnIce": "25:54", "assists": 1, "goals": 0, "shots": 1, "hits": 2, "powerPlayGoals": 0, "powerPlayAssists": 0, "penaltyMinutes": 0, "faceOffWins": 0, "faceoffTaken": 0, "takeaways": 1, "giveaways": 1, "shortHandedGoals": 0, "shortHandedAssists": 0, "blocked": 2, "plusMinus": 1, "evenTimeOnIce": "19:55", "powerPlayTimeOnIce": "2:15", "shortHandedTimeOnIce": "3:44"}}}, "ID8476873": {"person": {"id": 8476873, "fullName": "Mark Jankowski", "link": "/api/v1/people/8476873", "firstName": "Mark", "lastName": "Jankowski", "primaryNumber": "77", "birthDate": "1994-09-13", "currentAge": 24, "birthCity": "Hamilton", "birthStateProvince": "ON", "birthCountry": "CAN", "nationality": "CAN", "height": "6' 4\"", "weight": 202, "active": true, "alternateCaptain": false, "captain": false, "rookie": true, "shootsCatches": "L", "rosterStatus": "Y", "currentTeam": {"id": 20, "name": "Calgary Flames", "link": "/api/v1/teams/20"}, "primaryPosition": {"code": "C", "name": "Center", "type": "Forward", "abbreviation": "C"}}, "jerseyNumber": "77", "position": {"code": "C", "name": "Center", "type": "Forward", "abbreviation": "C"}, "stats": {"skaterStats": {"timeOnIce": "10:25", "assists": 0, "goals": 0, "shots": 2, "hits": 0, "powerPlayGoals": 0, "powerPlayAssists": 0, "penaltyMinutes": 0, "faceOffPct": 75.0, "faceOffWins": 3, "faceoffTaken": 4, "takeaways": 0, "giveaways": 0, "shortHandedGoals": 0, "shortHandedAssists": 0, "blocked": 1, "plusMinus": 0, "evenTimeOnIce": "7:55", "powerPlayTimeOnIce": "0:00", "shortHandedTimeOnIce": "2:30"}}}, "ID8474150": {"person": {"id": 8474150, "fullName": "Mikael Backlund", "link": "/api/v1/people/8474150", "firstName": "Mikael", "lastName": "Backlund", "primaryNumber": "11", "birthDate": "1989-03-17", "currentAge": 30, "birthCity": "Vasteras", "birthCountry": "SWE", "nationality": "SWE", "height": "6' 1\"", "weight": 199, "active": true, "alternateCaptain": false, "captain": false, "rookie": false, "shootsCatches": "L", "rosterStatus": "Y", "currentTeam": {"id": 20, "name": "Calgary Flames", "link": "/api/v1/teams/20"}, "primaryPosition": {"code": "C", "name": "Center", "type": "Forward", "abbreviation": "C"}}, "jerseyNumber": "11", "position": {"code": "C", "name": "Center", "type": "Forward", "abbreviation": "C"}, "stats": {"skaterStats": {"timeOnIce": "19:22", "assists": 0, "goals": 0, "shots": 3, "hits": 0, "powerPlayGoals": 0, "powerPlayAssists": 0, "penaltyMinutes": 0, "faceOffPct": 61.9, "faceOffWins": 13, "faceoffTaken": 21, "takeaways": 1, "giveaways": 0, "shortHandedGoals": 0, "shortHandedAssists": 0, "blocked": 1, "plusMinus": 0, "evenTimeOnIce": "14:45", "powerPlayTimeOnIce": "1:08", "shortHandedTimeOnIce": "3:29"}}}, "ID8476346": {"person": {"id": 8476346, "fullName": "Johnny Gaudreau", "link": "/api/v1/people/8476346", "firstName": "Johnny", "lastName": "Gaudreau", "primaryNumber": "13", "birthDate": "1993-08-13", "currentAge": 25, "birthCity": "Salem", "birthStateProvince": "NJ", "birthCountry": "USA", "nationality": "USA", "height": "5' 9\"", "weight": 157, "active": true, "alternateCaptain": false, "captain": false, "rookie": false, "shootsCatches": "L", "rosterStatus": "Y", "currentTeam": {"id": 20, "name": "Calgary Flames", "link": "/api/v1/teams/20"}, "primaryPosition": {"code": "L", "name": "Left Wing", "type": "Forward", "abbreviation": "LW"}}, "jerseyNumber": "13", "position": {"code": "L", "name": "Left Wing", "type": "Forward", "abbreviation": "LW"}, "stats": {"skaterStats": {"timeOnIce": "18:36", "assists": 2, "goals": 1, "shots": 1, "hits": 0, "powerPlayGoals": 0, "powerPlayAssists": 0, "penaltyMinutes": 0, "faceOffWins": 0, "faceoffTaken": 0, "takeaways": 0, "giveaways": 1, "shortHandedGoals": 0, "shortHandedAssists": 0, "blocked": 2, "plusMinus": 3, "evenTimeOnIce": "13:46", "powerPlayTimeOnIce": "4:50", "shortHandedTimeOnIce": "0:00"}}}, "ID8479314": {"person": {"id": 8479314, "fullName": "Matthew Tkachuk", "link": "/api/v1/people/8479314", "firstName": "Matthew", "lastName": "Tkachuk", "primaryNumber": "19", "birthDate": "1997-12-11", "currentAge": 21, "birthCity": "Scottsdale", "birthStateProvince": "AZ", "birthCountry": "USA", "nationality": "USA", "height": "6' 2\"", "weight": 202, "active": true, "alternateCaptain": false, "captain": false, "rookie": false, "shootsCatches": "L", "rosterStatus": "Y", "currentTeam": {"id": 20, "name": "Calgary Flames", "link": "/api/v1/teams/20"}, "primaryPosition": {"code": "L", "name": "Left Wing", "type": "Forward", "abbreviation": "LW"}}, "jerseyNumber": "19", "position": {"code": "L", "name": "Left Wing", "type": "Forward", "abbreviation": "LW"}, "stats": {"skaterStats": {"timeOnIce": "17:22", "assists": 0, "goals": 0, "shots": 2, "hits": 4, "powerPlayGoals": 0, "powerPlayAssists": 0, "penaltyMinutes": 0, "faceOffWins": 0, "faceoffTaken": 0, "takeaways": 0, "giveaways": 0, "shortHandedGoals": 0, "shortHandedAssists": 0, "blocked": 1, "plusMinus": 0, "evenTimeOnIce": "12:52", "powerPlayTimeOnIce": "4:30", "shortHandedTimeOnIce": "0:00"}}}, "ID8477497": {"person": {"id": 8477497, "fullName": "Sean Monahan", "link": "/api/v1/people/8477497", "firstName": "Sean", "lastName": "Monahan", "primaryNumber": "23", "birthDate": "1994-10-12", "currentAge": 24, "birthCity": "Brampton", "birthStateProvince": "ON", "birthCountry": "CAN", "nationality": "CAN", "height": "6' 3\"", "weight": 195, "active": true, "alternateCaptain": false, "captain": false, "rookie": false, "shootsCatches": "L", "rosterStatus": "Y", "currentTeam": {"id": 20, "name": "Calgary Flames", "link": "/api/v1/teams/20"}, "primaryPosition": {"code": "C", "name": "Center", "type": "Forward", "abbreviation": "C"}}, "jerseyNumber": "23", "position": {"code": "C", "name": "Center", "type": "Forward", "abbreviation": "C"}, "stats": {"skaterStats": {"timeOnIce": "18:31", "assists": 1, "goals": 1, "shots": 2, "hits": 2, "powerPlayGoals": 0, "powerPlayAssists": 0, "penaltyMinutes": 0, "faceOffPct": 42.86, "faceOffWins": 9, "faceoffTaken": 21, "takeaways": 4, "giveaways": 0, "shortHandedGoals": 0, "shortHandedAssists": 0, "blocked": 0, "plusMinus": 3, "evenTimeOnIce": "13:40", "powerPlayTimeOnIce": "4:50", "shortHandedTimeOnIce": "0:01"}}}, "ID8476462": {"person": {"id": 8476462, "fullName": "Dougie Hamilton", "link": "/api/v1/people/8476462", "firstName": "Dougie", "lastName": "Hamilton", "primaryNumber": "27", "birthDate": "1993-06-17", "currentAge": 25, "birthCity": "Toronto", "birthStateProvince": "ON", "birthCountry": "CAN", "nationality": "CAN", "height": "6' 6\"", "weight": 210, "active": true, "alternateCaptain": false, "captain": false, "rookie": false, "shootsCatches": "R", "rosterStatus": "Y", "currentTeam": {"id": 20, "name": "Calgary Flames", "link": "/api/v1/teams/20"}, "primaryPosition": {"code": "D", "name": "Defenseman", "type": "Defenseman", "abbreviation": "D"}}, "jerseyNumber": "27", "position": {"code": "D", "name": "Defenseman", "type": "Defenseman", "abbreviation": "D"}, "stats": {"skaterStats": {"timeOnIce": "18:58", "assists": 0, "goals": 1, "shots": 3, "hits": 1, "powerPlayGoals": 0, "powerPlayAssists": 0, "penaltyMinutes": 2, "faceOffPct": 0.0, "faceOffWins": 0, "faceoffTaken": 1, "takeaways": 0, "giveaways": 0, "shortHandedGoals": 0, "shortHandedAssists": 0, "blocked": 1, "plusMinus": 1, "evenTimeOnIce": "15:57", "powerPlayTimeOnIce": "2:11", "shortHandedTimeOnIce": "0:50"}}}, "ID8470162": {"person": {"id": 8470162, "fullName": "Matt Stajan", "link": "/api/v1/people/8470162", "firstName": "Matt", "lastName": "Stajan", "primaryNumber": "18", "birthDate": "1983-12-19", "currentAge": 35, "birthCity": "Mississauga", "birthStateProvince": "ON", "birthCountry": "CAN", "nationality": "CAN", "height": "6' 1\"", "weight": 195, "active": true, "alternateCaptain": false, "captain": false, "rookie": false, "shootsCatches": "L", "rosterStatus": "Y", "currentTeam": {"id": 20, "name": "Calgary Flames", "link": "/api/v1/teams/20"}, "primaryPosition": {"code": "C", "name": "Center", "type": "Forward", "abbreviation": "C"}}, "jerseyNumber": "18", "position": {"code": "C", "name": "Center", "type": "Forward", "abbreviation": "C"}, "stats": {"skaterStats": {"timeOnIce": "12:08", "assists": 0, "goals": 0, "shots": 0, "hits": 0, "powerPlayGoals": 0, "powerPlayAssists": 0, "penaltyMinutes": 0, "faceOffPct": 50.0, "faceOffWins": 3, "faceoffTaken": 6, "takeaways": 0, "giveaways": 1, "shortHandedGoals": 0, "shortHandedAssists": 0, "blocked": 1, "plusMinus": -1, "evenTimeOnIce": "8:56", "powerPlayTimeOnIce": "0:00", "shortHandedTimeOnIce": "3:12"}}}, "ID8479066": {"person": {"id": 8479066, "fullName": "Ryan Lomberg", "link": "/api/v1/people/8479066", "firstName": "Ryan", "lastName": "Lomberg", "primaryNumber": "56", "birthDate": "1994-12-09", "currentAge": 24, "birthCity": "Richmond Hill", "birthStateProvince": "ON", "birthCountry": "CAN", "nationality": "CAN", "height": "5' 9\"", "weight": 187, "active": true, "alternateCaptain": false, "captain": false, "rookie": true, "shootsCatches": "L", "rosterStatus": "Y", "currentTeam": {"id": 20, "name": "Calgary Flames", "link": "/api/v1/teams/20"}, "primaryPosition": {"code": "L", "name": "Left Wing", "type": "Forward", "abbreviation": "LW"}}, "jerseyNumber": "56", "position": {"code": "N/A", "name": "Unknown", "type": "Unknown", "abbreviation": "N/A"}, "stats": {}}}, "goalies": [8469608], "skaters": [8470966, 8474673, 8474150, 8476346, 8470162, 8479314, 8477508, 8477903, 8477497, 8474612, 8474628, 8476462, 8471426, 8476967, 8473564, 8476873, 8475907, 8477935, 8474749, 8475949, 8479066], "onIce": [8469608, 8473564, 8474150, 8474612, 8474673, 8479314], "onIcePlus": [{"playerId": 8474612, "shiftDuration": 7, "stamina": 100}, {"playerId": 8479314, "shiftDuration": 7, "stamina": 100}, {"playerId": 8474673, "shiftDuration": 7, "stamina": 100}, {"playerId": 8469608, "shiftDuration": 526, "stamina": 33}, {"playerId": 8474150, "shiftDuration": 7, "stamina": 100}, {"playerId": 8473564, "shiftDuration": 7, "stamina": 100}], "scratches": [8474749, 8475949, 8479066], "penaltyBox": [], "coaches": [{"person": {"fullName": "Glen Gulutzan", "link": "/api/v1/people/null"}, "position": {"code": "HC", "name": "Head Coach", "type": "Head Coach", "abbreviation": "Head Coach"}}]}, "home": {"team": {"id": 16, "name": "Chicago Blackhawks", "link": "/api/v1/teams/16"}, "teamStats": {"teamSkaterStats": {"goals": 2, "pim": 10, "shots": 36, "powerPlayPercentage": "20.0", "powerPlayGoals": 1.0, "powerPlayOpportunities": 5.0, "faceOffWinPercentage": "50.8", "blocked": 27, "takeaways": 13, "giveaways": 5, "hits": 7}}, "players": {"ID8480172": {"person": {"id": 8480172, "fullName": "Jan Rutta", "link": "/api/v1/people/8480172", "firstName": "Jan", "lastName": "Rutta", "primaryNumber": "44", "birthDate": "1990-07-29", "currentAge": 28, "birthCity": "P\u00edsek", "birthCountry": "CZE", "nationality": "CZE", "height": "6' 3\"", "weight": 200, "active": true, "alternateCaptain": false, "captain": false, "rookie": false, "shootsCatches": "R", "rosterStatus": "I", "currentTeam": {"id": 16, "name": "Chicago Blackhawks", "link": "/api/v1/teams/16"}, "primaryPosition": {"code": "D", "name": "Defenseman", "type": "Defenseman", "abbreviation": "D"}}, "jerseyNumber": "44", "position": {"code": "D", "name": "Defenseman", "type": "Defenseman", "abbreviation": "D"}, "stats": {"skaterStats": {"timeOnIce": "14:32", "assists": 0, "goals": 0, "shots": 1, "hits": 0, "powerPlayGoals": 0, "powerPlayAssists": 0, "penaltyMinutes": 0, "faceOffWins": 0, "faceoffTaken": 0, "takeaways": 0, "giveaways": 2, "shortHandedGoals": 0, "shortHandedAssists": 0, "blocked": 2, "plusMinus": 0, "evenTimeOnIce": "10:29", "powerPlayTimeOnIce": "0:03", "shortHandedTimeOnIce": "4:00"}}}, "ID8474739": {"person": {"id": 8474739, "fullName": "Tommy Wingels", "link": "/api/v1/people/8474739", "firstName": "Tommy", "lastName": "Wingels", "primaryNumber": "57", "birthDate": "1988-04-12", "currentAge": 30, "birthCity": "Evanston", "birthStateProvince": "IL", "birthCountry": "USA", "nationality": "USA", "height": "6' 0\"", "weight": 200, "active": true, "alternateCaptain": false, "captain": false, "rookie": false, "shootsCatches": "R", "rosterStatus": "Y", "currentTeam": {"id": 16, "name": "Chicago Blackhawks", "link": "/api/v1/teams/16"}, "primaryPosition": {"code": "R", "name": "Right Wing", "type": "Forward", "abbreviation": "RW"}}, "jerseyNumber": "57", "position": {"code": "N/A", "name": "Unknown", "type": "Unknown", "abbreviation": "N/A"}, "stats": {}}, "ID8470607": {"person": {"id": 8470607, "fullName": "Brent Seabrook", "link": "/api/v1/people/8470607", "firstName": "Brent", "lastName": "Seabrook", "primaryNumber": "7", "birthDate": "1985-04-20", "currentAge": 33, "birthCity": "Richmond", "birthStateProvince": "BC", "birthCountry": "CAN", "nationality": "CAN", "height": "6' 3\"", "weight": 220, "active": true, "alternateCaptain": true, "captain": false, "rookie": false, "shootsCatches": "R", "rosterStatus": "Y", "currentTeam": {"id": 16, "name": "Chicago Blackhawks", "link": "/api/v1/teams/16"}, "primaryPosition": {"code": "D", "name": "Defenseman", "type": "Defenseman", "abbreviation": "D"}}, "jerseyNumber": "7", "position": {"code": "D", "name": "Defenseman", "type": "Defenseman", "abbreviation": "D"}, "stats": {"skaterStats": {"timeOnIce": "22:28", "assists": 0, "goals": 0, "shots": 2, "hits": 1, "powerPlayGoals": 0, "powerPlayAssists": 0, "penaltyMinutes": 2, "faceOffWins": 0, "faceoffTaken": 0, "takeaways": 1, "giveaways": 0, "shortHandedGoals": 0, "shortHandedAssists": 0, "blocked": 4, "plusMinus": 0, "evenTimeOnIce": "16:16", "powerPlayTimeOnIce": "4:49", "shortHandedTimeOnIce": "1:23"}}}, "ID8476979": {"person": {"id": 8476979, "fullName": "Erik Gustafsson", "link": "/api/v1/people/8476979", "firstName": "Erik", "lastName": "Gustafsson", "primaryNumber": "56", "birthDate": "1992-03-14", "currentAge": 27, "birthCity": "Nynashamn", "birthCountry": "SWE", "nationality": "SWE", "height": "6' 0\"", "weight": 176, "active": true, "alternateCaptain": false, "captain": false, "rookie": false, "shootsCatches": "L", "rosterStatus": "Y", "currentTeam": {"id": 16, "name": "Chicago Blackhawks", "link": "/api/v1/teams/16"}, "primaryPosition": {"code": "D", "name": "Defenseman", "type": "Defenseman", "abbreviation": "D"}}, "jerseyNumber": "56", "position": {"code": "D", "name": "Defenseman", "type": "Defenseman", "abbreviation": "D"}, "stats": {"skaterStats": {"timeOnIce": "16:31", "assists": 0, "goals": 0, "shots": 0, "hits": 0, "powerPlayGoals": 0, "powerPlayAssists": 0, "penaltyMinutes": 2, "faceOffWins": 0, "faceoffTaken": 0, "takeaways": 0, "giveaways": 0, "shortHandedGoals": 0, "shortHandedAssists": 0, "blocked": 1, "plusMinus": 0, "evenTimeOnIce": "15:46", "powerPlayTimeOnIce": "0:37", "shortHandedTimeOnIce": "0:08"}}}, "ID8477407": {"person": {"id": 8477407, "fullName": "Anthony Duclair", "link": "/api/v1/people/8477407", "firstName": "Anthony", "lastName": "Duclair", "primaryNumber": "91", "birthDate": "1995-08-26", "currentAge": 23, "birthCity": "Pointe-Claire", "birthStateProvince": "QC", "birthCountry": "CAN", "nationality": "CAN", "height": "5' 11\"", "weight": 191, "active": true, "alternateCaptain": false, "captain": false, "rookie": false, "shootsCatches": "L", "rosterStatus": "Y", "currentTeam": {"id": 16, "name": "Chicago Blackhawks", "link": "/api/v1/teams/16"}, "primaryPosition": {"code": "L", "name": "Left Wing", "type": "Forward", "abbreviation": "LW"}}, "jerseyNumber": "91", "position": {"code": "L", "name": "Left Wing", "type": "Forward", "abbreviation": "LW"}, "stats": {"skaterStats": {"timeOnIce": "16:04", "assists": 0, "goals": 0, "shots": 0, "hits": 1, "powerPlayGoals": 0, "powerPlayAssists": 0, "penaltyMinutes": 0, "faceOffWins": 0, "faceoffTaken": 0, "takeaways": 0, "giveaways": 0, "shortHandedGoals": 0, "shortHandedAssists": 0, "blocked": 1, "plusMinus": -2, "evenTimeOnIce": "11:55", "powerPlayTimeOnIce": "4:09", "shortHandedTimeOnIce": "0:00"}}}, "ID8471301": {"person": {"id": 8471301, "fullName": "Jeff Glass", "link": "/api/v1/people/8471301", "firstName": "Jeff", "lastName": "Glass", "primaryNumber": "30", "birthDate": "1985-11-19", "currentAge": 33, "birthCity": "Calgary", "birthStateProvince": "AB", "birthCountry": "CAN", "nationality": "CAN", "height": "6' 3\"", "weight": 206, "active": true, "alternateCaptain": false, "captain": false, "rookie": false, "shootsCatches": "L", "rosterStatus": "Y", "currentTeam": {"id": 16, "name": "Chicago Blackhawks", "link": "/api/v1/teams/16"}, "primaryPosition": {"code": "G", "name": "Goalie", "type": "Goalie", "abbreviation": "G"}}, "jerseyNumber": "30", "position": {"code": "G", "name": "Goalie", "type": "Goalie", "abbreviation": "G"}, "stats": {"goalieStats": {"timeOnIce": "58:14", "assists": 0, "goals": 0, "pim": 0, "shots": 22, "saves": 20, "powerPlaySaves": 5, "shortHandedSaves": 2, "evenSaves": 13, "shortHandedShotsAgainst": 2, "evenShotsAgainst": 15, "powerPlayShotsAgainst": 5, "decision": "L", "savePercentage": 90.9090909090909, "powerPlaySavePercentage": 100.0, "shortHandedSavePercentage": 100.0, "evenStrengthSavePercentage": 86.66666666666667}}}, "ID8473604": {"person": {"id": 8473604, "fullName": "Jonathan Toews", "link": "/api/v1/people/8473604", "firstName": "Jonathan", "lastName": "Toews", "primaryNumber": "19", "birthDate": "1988-04-29", "currentAge": 30, "birthCity": "Winnipeg", "birthStateProvince": "MB", "birthCountry": "CAN", "nationality": "CAN", "height": "6' 2\"", "weight": 201, "active": true, "alternateCaptain": false, "captain": true, "rookie": false, "shootsCatches": "L", "rosterStatus": "Y", "currentTeam": {"id": 16, "name": "Chicago Blackhawks", "link": "/api/v1/teams/16"}, "primaryPosition": {"code": "C", "name": "Center", "type": "Forward", "abbreviation": "C"}}, "jerseyNumber": "19", "position": {"code": "C", "name": "Center", "type": "Forward", "abbreviation": "C"}, "stats": {"skaterStats": {"timeOnIce": "19:50", "assists": 1, "goals": 0, "shots": 1, "hits": 0, "powerPlayGoals": 0, "powerPlayAssists": 1, "penaltyMinutes": 0, "faceOffPct": 69.23, "faceOffWins": 18, "faceoffTaken": 26, "takeaways": 2, "giveaways": 0, "shortHandedGoals": 0, "shortHandedAssists": 0, "blocked": 0, "plusMinus": -2, "evenTimeOnIce": "12:36", "powerPlayTimeOnIce": "4:50", "shortHandedTimeOnIce": "2:24"}}}, "ID8474642": {"person": {"id": 8474642, "fullName": "Lance Bouma", "link": "/api/v1/people/8474642", "firstName": "Lance", "lastName": "Bouma", "primaryNumber": "17", "birthDate": "1990-03-25", "currentAge": 29, "birthCity": "Provost", "birthStateProvince": "AB", "birthCountry": "CAN", "nationality": "CAN", "height": "6' 2\"", "weight": 208, "active": true, "alternateCaptain": false, "captain": false, "rookie": false, "shootsCatches": "L", "rosterStatus": "Y", "currentTeam": {"id": 16, "name": "Chicago Blackhawks", "link": "/api/v1/teams/16"}, "primaryPosition": {"code": "L", "name": "Left Wing", "type": "Forward", "abbreviation": "LW"}}, "jerseyNumber": "17", "position": {"code": "N/A", "name": "Unknown", "type": "Unknown", "abbreviation": "N/A"}, "stats": {}}, "ID8476438": {"person": {"id": 8476438, "fullName": "Brandon Saad", "link": "/api/v1/people/8476438", "firstName": "Brandon", "lastName": "Saad", "primaryNumber": "20", "birthDate": "1992-10-27", "currentAge": 26, "birthCity": "Pittsburgh", "birthStateProvince": "PA", "birthCountry": "USA", "nationality": "USA", "height": "6' 1\"", "weight": 206, "active": true, "alternateCaptain": false, "captain": false, "rookie": false, "shootsCatches": "L", "rosterStatus": "Y", "currentTeam": {"id": 16, "name": "Chicago Blackhawks", "link": "/api/v1/teams/16"}, "primaryPosition": {"code": "L", "name": "Left Wing", "type": "Forward", "abbreviation": "LW"}}, "jerseyNumber": "20", "position": {"code": "L", "name": "Left Wing", "type": "Forward", "abbreviation": "LW"}, "stats": {"skaterStats": {"timeOnIce": "9:54", "assists": 0, "goals": 0, "shots": 0, "hits": 0, "powerPlayGoals": 0, "powerPlayAssists": 0, "penaltyMinutes": 0, "faceOffWins": 0, "faceoffTaken": 0, "takeaways": 2, "giveaways": 0, "shortHandedGoals": 0, "shortHandedAssists": 0, "blocked": 2, "plusMinus": 0, "evenTimeOnIce": "7:37", "powerPlayTimeOnIce": "0:01", "shortHandedTimeOnIce": "2:16"}}}, "ID8479337": {"person": {"id": 8479337, "fullName": "Alex DeBrincat", "link": "/api/v1/people/8479337", "firstName": "Alex", "lastName": "DeBrincat", "primaryNumber": "12", "birthDate": "1997-12-18", "currentAge": 21, "birthCity": "Farmington Hills", "birthStateProvince": "MI", "birthCountry": "USA", "nationality": "USA", "height": "5' 7\"", "weight": 165, "active": true, "alternateCaptain": false, "captain": false, "rookie": true, "shootsCatches": "R", "rosterStatus": "Y", "currentTeam": {"id": 16, "name": "Chicago Blackhawks", "link": "/api/v1/teams/16"}, "primaryPosition": {"code": "R", "name": "Right Wing", "type": "Forward", "abbreviation": "RW"}}, "jerseyNumber": "12", "position": {"code": "R", "name": "Right Wing", "type": "Forward", "abbreviation": "RW"}, "stats": {"skaterStats": {"timeOnIce": "17:25", "assists": 0, "goals": 1, "shots": 6, "hits": 0, "powerPlayGoals": 1, "powerPlayAssists": 0, "penaltyMinutes": 0, "faceOffPct": 0.0, "faceOffWins": 0, "faceoffTaken": 1, "takeaways": 0, "giveaways": 0, "shortHandedGoals": 0, "shortHandedAssists": 0, "blocked": 3, "plusMinus": -2, "evenTimeOnIce": "12:23", "powerPlayTimeOnIce": "5:02", "shortHandedTimeOnIce": "0:00"}}}, "ID8477851": {"person": {"id": 8477851, "fullName": "Jordan Oesterle", "link": "/api/v1/people/8477851", "firstName": "Jordan", "lastName": "Oesterle", "primaryNumber": "82", "birthDate": "1992-06-25", "currentAge": 26, "birthCity": "Dearborn Heights", "birthStateProvince": "MI", "birthCountry": "USA", "nationality": "USA", "height": "6' 0\"", "weight": 182, "active": true, "alternateCaptain": false, "captain": false, "rookie": false, "shootsCatches": "L", "rosterStatus": "Y", "currentTeam": {"id": 16, "name": "Chicago Blackhawks", "link": "/api/v1/teams/16"}, "primaryPosition": {"code": "D", "name": "Defenseman", "type": "Defenseman", "abbreviation": "D"}}, "jerseyNumber": "82", "position": {"code": "D", "name": "Defenseman", "type": "Defenseman", "abbreviation": "D"}, "stats": {"skaterStats": {"timeOnIce": "26:06", "assists": 1, "goals": 0, "shots": 1, "hits": 1, "powerPlayGoals": 0, "powerPlayAssists": 1, "penaltyMinutes": 0, "faceOffWins": 0, "faceoffTaken": 0, "takeaways": 2, "giveaways": 1, "shortHandedGoals": 0, "shortHandedAssists": 0, "blocked": 7, "plusMinus": -2, "evenTimeOnIce": "17:45", "powerPlayTimeOnIce": "5:11", "shortHandedTimeOnIce": "3:10"}}}, "ID8470281": {"person": {"id": 8470281, "fullName": "Duncan Keith", "link": "/api/v1/people/8470281", "firstName": "Duncan", "lastName": "Keith", "primaryNumber": "2", "birthDate": "1983-07-16", "currentAge": 35, "birthCity": "Winnipeg", "birthStateProvince": "MB", "birthCountry": "CAN", "nationality": "CAN", "height": "6' 1\"", "weight": 192, "active": true, "alternateCaptain": true, "captain": false, "rookie": false, "shootsCatches": "L", "rosterStatus": "Y", "currentTeam": {"id": 16, "name": "Chicago Blackhawks", "link": "/api/v1/teams/16"}, "primaryPosition": {"code": "D", "name": "Defenseman", "type": "Defenseman", "abbreviation": "D"}}, "jerseyNumber": "2", "position": {"code": "D", "name": "Defenseman", "type": "Defenseman", "abbreviation": "D"}, "stats": {"skaterStats": {"timeOnIce": "22:03", "assists": 0, "goals": 0, "shots": 3, "hits": 0, "powerPlayGoals": 0, "powerPlayAssists": 0, "penaltyMinutes": 0, "faceOffWins": 0, "faceoffTaken": 0, "takeaways": 2, "giveaways": 0, "shortHandedGoals": 0, "shortHandedAssists": 0, "blocked": 4, "plusMinus": -2, "evenTimeOnIce": "18:57", "powerPlayTimeOnIce": "0:18", "shortHandedTimeOnIce": "2:48"}}}, "ID8474141": {"person": {"id": 8474141, "fullName": "Patrick Kane", "link": "/api/v1/people/8474141", "firstName": "Patrick", "lastName": "Kane", "primaryNumber": "88", "birthDate": "1988-11-19", "currentAge": 30, "birthCity": "Buffalo", "birthStateProvince": "NY", "birthCountry": "USA", "nationality": "USA", "height": "5' 11\"", "weight": 177, "active": true, "alternateCaptain": false, "captain": false, "rookie": false, "shootsCatches": "L", "rosterStatus": "Y", "currentTeam": {"id": 16, "name": "Chicago Blackhawks", "link": "/api/v1/teams/16"}, "primaryPosition": {"code": "R", "name": "Right Wing", "type": "Forward", "abbreviation": "RW"}}, "jerseyNumber": "88", "position": {"code": "R", "name": "Right Wing", "type": "Forward", "abbreviation": "RW"}, "stats": {"skaterStats": {"timeOnIce": "22:21", "assists": 0, "goals": 1, "shots": 4, "hits": 0, "powerPlayGoals": 0, "powerPlayAssists": 0, "penaltyMinutes": 0, "faceOffWins": 0, "faceoffTaken": 0, "takeaways": 0, "giveaways": 0, "shortHandedGoals": 0, "shortHandedAssists": 0, "blocked": 0, "plusMinus": 0, "evenTimeOnIce": "17:14", "powerPlayTimeOnIce": "5:07", "shortHandedTimeOnIce": "0:00"}}}, "ID8476994": {"person": {"id": 8476994, "fullName": "Vinnie Hinostroza", "link": "/api/v1/people/8476994", "firstName": "Vinnie", "lastName": "Hinostroza", "primaryNumber": "48", "birthDate": "1994-04-03", "currentAge": 25, "birthCity": "Chicago", "birthStateProvince": "IL", "birthCountry": "USA", "nationality": "USA", "height": "5' 9\"", "weight": 173, "active": true, "alternateCaptain": false, "captain": false, "rookie": false, "shootsCatches": "R", "rosterStatus": "Y", "currentTeam": {"id": 16, "name": "Chicago Blackhawks", "link": "/api/v1/teams/16"}, "primaryPosition": {"code": "L", "name": "Left Wing", "type": "Forward", "abbreviation": "LW"}}, "jerseyNumber": "48", "position": {"code": "L", "name": "Left Wing", "type": "Forward", "abbreviation": "LW"}, "stats": {"skaterStats": {"timeOnIce": "14:31", "assists": 0, "goals": 0, "shots": 3, "hits": 0, "powerPlayGoals": 0, "powerPlayAssists": 0, "penaltyMinutes": 0, "faceOffPct": 0.0, "faceOffWins": 0, "faceoffTaken": 1, "takeaways": 1, "giveaways": 0, "shortHandedGoals": 0, "shortHandedAssists": 0, "blocked": 0, "plusMinus": -1, "evenTimeOnIce": "10:44", "powerPlayTimeOnIce": "3:47", "shortHandedTimeOnIce": "0:00"}}}, "ID8477951": {"person": {"id": 8477951, "fullName": "Nick Schmaltz", "link": "/api/v1/people/8477951", "firstName": "Nick", "lastName": "Schmaltz", "primaryNumber": "8", "birthDate": "1996-02-23", "currentAge": 23, "birthCity": "Madison", "birthStateProvince": "WI", "birthCountry": "USA", "nationality": "USA", "height": "6' 0\"", "weight": 177, "active": true, "alternateCaptain": false, "captain": false, "rookie": false, "shootsCatches": "R", "rosterStatus": "Y", "currentTeam": {"id": 16, "name": "Chicago Blackhawks", "link": "/api/v1/teams/16"}, "primaryPosition": {"code": "C", "name": "Center", "type": "Forward", "abbreviation": "C"}}, "jerseyNumber": "8", "position": {"code": "C", "name": "Center", "type": "Forward", "abbreviation": "C"}, "stats": {"skaterStats": {"timeOnIce": "22:39", "assists": 1, "goals": 0, "shots": 2, "hits": 0, "powerPlayGoals": 0, "powerPlayAssists": 0, "penaltyMinutes": 0, "faceOffPct": 30.0, "faceOffWins": 3, "faceoffTaken": 10, "takeaways": 1, "giveaways": 0, "shortHandedGoals": 0, "shortHandedAssists": 0, "blocked": 0, "plusMinus": 0, "evenTimeOnIce": "16:35", "powerPlayTimeOnIce": "4:26", "shortHandedTimeOnIce": "1:38"}}}, "ID8477451": {"person": {"id": 8477451, "fullName": "Ryan Hartman", "link": "/api/v1/people/8477451", "firstName": "Ryan", "lastName": "Hartman", "primaryNumber": "38", "birthDate": "1994-09-20", "currentAge": 24, "birthCity": "Hilton Head Isl.", "birthStateProvince": "SC", "birthCountry": "USA", "nationality": "USA", "height": "6' 0\"", "weight": 181, "active": true, "alternateCaptain": false, "captain": false, "rookie": false, "shootsCatches": "R", "rosterStatus": "Y", "currentTeam": {"id": 16, "name": "Chicago Blackhawks", "link": "/api/v1/teams/16"}, "primaryPosition": {"code": "L", "name": "Left Wing", "type": "Forward", "abbreviation": "LW"}}, "jerseyNumber": "38", "position": {"code": "L", "name": "Left Wing", "type": "Forward", "abbreviation": "LW"}, "stats": {"skaterStats": {"timeOnIce": "11:40", "assists": 0, "goals": 0, "shots": 3, "hits": 1, "powerPlayGoals": 0, "powerPlayAssists": 0, "penaltyMinutes": 2, "faceOffPct": 60.0, "faceOffWins": 3, "faceoffTaken": 5, "takeaways": 0, "giveaways": 0, "shortHandedGoals": 0, "shortHandedAssists": 0, "blocked": 0, "plusMinus": 0, "evenTimeOnIce": "7:51", "powerPlayTimeOnIce": "3:49", "shortHandedTimeOnIce": "0:00"}}}, "ID8473573": {"person": {"id": 8473573, "fullName": "Artem Anisimov", "link": "/api/v1/people/8473573", "firstName": "Artem", "lastName": "Anisimov", "primaryNumber": "15", "birthDate": "1988-05-24", "currentAge": 30, "birthCity": "Yaroslavl", "birthCountry": "RUS", "nationality": "RUS", "height": "6' 4\"", "weight": 198, "active": true, "alternateCaptain": false, "captain": false, "rookie": false, "shootsCatches": "L", "rosterStatus": "Y", "currentTeam": {"id": 16, "name": "Chicago Blackhawks", "link": "/api/v1/teams/16"}, "primaryPosition": {"code": "C", "name": "Center", "type": "Forward", "abbreviation": "C"}}, "jerseyNumber": "15", "position": {"code": "C", "name": "Center", "type": "Forward", "abbreviation": "C"}, "stats": {"skaterStats": {"timeOnIce": "19:42", "assists": 1, "goals": 0, "shots": 1, "hits": 0, "powerPlayGoals": 0, "powerPlayAssists": 0, "penaltyMinutes": 2, "faceOffPct": 50.0, "faceOffWins": 4, "faceoffTaken": 8, "takeaways": 0, "giveaways": 0, "shortHandedGoals": 0, "shortHandedAssists": 0, "blocked": 0, "plusMinus": 1, "evenTimeOnIce": "13:32", "powerPlayTimeOnIce": "4:14", "shortHandedTimeOnIce": "1:56"}}}, "ID8476473": {"person": {"id": 8476473, "fullName": "Connor Murphy", "link": "/api/v1/people/8476473", "firstName": "Connor", "lastName": "Murphy", "primaryNumber": "5", "birthDate": "1993-03-26", "currentAge": 26, "birthCity": "Dublin", "birthStateProvince": "OH", "birthCountry": "USA", "nationality": "USA", "height": "6' 4\"", "weight": 212, "active": true, "alternateCaptain": false, "captain": false, "rookie": false, "shootsCatches": "R", "rosterStatus": "Y", "currentTeam": {"id": 16, "name": "Chicago Blackhawks", "link": "/api/v1/teams/16"}, "primaryPosition": {"code": "D", "name": "Defenseman", "type": "Defenseman", "abbreviation": "D"}}, "jerseyNumber": "5", "position": {"code": "N/A", "name": "Unknown", "type": "Unknown", "abbreviation": "N/A"}, "stats": {}}, "ID8476430": {"person": {"id": 8476430, "fullName": "Tomas Jurco", "link": "/api/v1/people/8476430", "firstName": "Tomas", "lastName": "Jurco", "primaryNumber": "13", "birthDate": "1992-12-28", "currentAge": 26, "birthCity": "Kosice", "birthCountry": "SVK", "nationality": "SVK", "height": "6' 2\"", "weight": 188, "active": true, "alternateCaptain": false, "captain": false, "rookie": false, "shootsCatches": "L", "rosterStatus": "Y", "currentTeam": {"id": 16, "name": "Chicago Blackhawks", "link": "/api/v1/teams/16"}, "primaryPosition": {"code": "L", "name": "Left Wing", "type": "Forward", "abbreviation": "LW"}}, "jerseyNumber": "13", "position": {"code": "L", "name": "Left Wing", "type": "Forward", "abbreviation": "LW"}, "stats": {"skaterStats": {"timeOnIce": "8:24", "assists": 0, "goals": 0, "shots": 3, "hits": 0, "powerPlayGoals": 0, "powerPlayAssists": 0, "penaltyMinutes": 2, "faceOffWins": 0, "faceoffTaken": 0, "takeaways": 0, "giveaways": 0, "shortHandedGoals": 0, "shortHandedAssists": 0, "blocked": 1, "plusMinus": 0, "evenTimeOnIce": "8:24", "powerPlayTimeOnIce": "0:00", "shortHandedTimeOnIce": "0:00"}}}, "ID8480144": {"person": {"id": 8480144, "fullName": "David Kampf", "link": "/api/v1/people/8480144", "firstName": "David", "lastName": "Kampf", "primaryNumber": "64", "birthDate": "1995-01-12", "currentAge": 24, "birthCity": "Chomutov", "birthCountry": "CZE", "nationality": "CZE", "height": "6' 2\"", "weight": 195, "active": true, "alternateCaptain": false, "captain": false, "rookie": true, "shootsCatches": "L", "rosterStatus": "Y", "currentTeam": {"id": 16, "name": "Chicago Blackhawks", "link": "/api/v1/teams/16"}, "primaryPosition": {"code": "C", "name": "Center", "type": "Forward", "abbreviation": "C"}}, "jerseyNumber": "64", "position": {"code": "C", "name": "Center", "type": "Forward", "abbreviation": "C"}, "stats": {"skaterStats": {"timeOnIce": "11:23", "assists": 0, "goals": 0, "shots": 1, "hits": 1, "powerPlayGoals": 0, "powerPlayAssists": 0, "penaltyMinutes": 0, "faceOffPct": 33.33, "faceOffWins": 4, "faceoffTaken": 12, "takeaways": 1, "giveaways": 0, "shortHandedGoals": 0, "shortHandedAssists": 0, "blocked": 1, "plusMinus": 0, "evenTimeOnIce": "9:28", "powerPlayTimeOnIce": "0:01", "shortHandedTimeOnIce": "1:54"}}}, "ID8479482": {"person": {"id": 8479482, "fullName": "Michal Kempny", "link": "/api/v1/people/8479482", "firstName": "Michal", "lastName": "Kempny", "primaryNumber": "6", "birthDate": "1990-09-08", "currentAge": 28, "birthCity": "Hodonin", "birthCountry": "CZE", "nationality": "CZE", "height": "6' 0\"", "weight": 194, "active": true, "alternateCaptain": false, "captain": false, "rookie": false, "shootsCatches": "L", "rosterStatus": "Y", "currentTeam": {"id": 16, "name": "Chicago Blackhawks", "link": "/api/v1/teams/16"}, "primaryPosition": {"code": "D", "name": "Defenseman", "type": "Defenseman", "abbreviation": "D"}}, "jerseyNumber": "6", "position": {"code": "D", "name": "Defenseman", "type": "Defenseman", "abbreviation": "D"}, "stats": {"skaterStats": {"timeOnIce": "10:51", "assists": 0, "goals": 0, "shots": 3, "hits": 0, "powerPlayGoals": 0, "powerPlayAssists": 0, "penaltyMinutes": 0, "faceOffWins": 0, "faceoffTaken": 0, "takeaways": 1, "giveaways": 0, "shortHandedGoals": 0, "shortHandedAssists": 0, "blocked": 1, "plusMinus": 0, "evenTimeOnIce": "10:16", "powerPlayTimeOnIce": "0:00", "shortHandedTimeOnIce": "0:35"}}}, "ID8469544": {"person": {"id": 8469544, "fullName": "Patrick Sharp", "link": "/api/v1/people/8469544", "firstName": "Patrick", "lastName": "Sharp", "primaryNumber": "10", "birthDate": "1981-12-27", "currentAge": 37, "birthCity": "Winnipeg", "birthStateProvince": "MB", "birthCountry": "CAN", "nationality": "CAN", "height": "6' 1\"", "weight": 200, "active": true, "alternateCaptain": false, "captain": false, "rookie": false, "shootsCatches": "R", "rosterStatus": "Y", "currentTeam": {"id": 16, "name": "Chicago Blackhawks", "link": "/api/v1/teams/16"}, "primaryPosition": {"code": "L", "name": "Left Wing", "type": "Forward", "abbreviation": "LW"}}, "jerseyNumber": "10", "position": {"code": "L", "name": "Left Wing", "type": "Forward", "abbreviation": "LW"}, "stats": {"skaterStats": {"timeOnIce": "7:22", "assists": 0, "goals": 0, "shots": 2, "hits": 2, "powerPlayGoals": 0, "powerPlayAssists": 0, "penaltyMinutes": 0, "faceOffWins": 0, "faceoffTaken": 0, "takeaways": 0, "giveaways": 0, "shortHandedGoals": 0, "shortHandedAssists": 0, "blocked": 0, "plusMinus": 0, "evenTimeOnIce": "7:21", "powerPlayTimeOnIce": "0:01", "shortHandedTimeOnIce": "0:00"}}}}, "goalies": [8471301], "skaters": [8470281, 8479482, 8470607, 8477951, 8469544, 8479337, 8476430, 8473573, 8473604, 8476438, 8477451, 8480172, 8476994, 8476979, 8480144, 8477851, 8474141, 8477407, 8474642, 8476473, 8474739], "onIce": [8470281, 8473604, 8474141, 8477407, 8477951, 8479337], "onIcePlus": [{"playerId": 8470281, "shiftDuration": 7, "stamina": 100}, {"playerId": 8474141, "shiftDuration": 87, "stamina": 33}, {"playerId": 8477951, "shiftDuration": 59, "stamina": 66}, {"playerId": 8479337, "shiftDuration": 7, "stamina": 100}, {"playerId": 8473604, "shiftDuration": 7, "stamina": 100}, {"playerId": 8477407, "shiftDuration": 7, "stamina": 100}], "scratches": [8474642, 8476473, 8474739], "penaltyBox": [], "coaches": [{"person": {"fullName": "Joel Quenneville", "link": "/api/v1/people/null"}, "position": {"code": "HC", "name": "Head Coach", "type": "Head Coach", "abbreviation": "Head Coach"}}]}}, "officials": [{"official": {"id": 4600, "fullName": "Francis Charron", "link": "/api/v1/people/4600"}, "officialType": "Referee"}, {"official": {"id": 4691, "fullName": "Garrett Rank", "link": "/api/v1/people/4691"}, "officialType": "Referee"}, {"official": {"id": 7206, "fullName": "Travis Gawryletz", "link": "/api/v1/people/7206"}, "officialType": "Linesman"}, {"official": {"id": 2328, "fullName": "Vaughan Rody", "link": "/api/v1/people/2328"}, "officialType": "Linesman"}]}